{
  "updated_at": "2025-12-29 15:40:39 UTC",
  "count": 270,
  "source": "OKX SWAP",
  "prices": {
    "MOG-USDT-SWAP": "0.0000002331",
    "WIF-USDT-SWAP": "0.2943",
    "PI-USDT-SWAP": "0.2026",
    "RECALL-USDT-SWAP": "0.09648",
    "SUSHI-USDT-SWAP": "0.2962",
    "RAVE-USDT-SWAP": "0.44171",
    "XLM-USDT-SWAP": "0.21918",
    "DASH-USDT-SWAP": "42.51",
    "TRUST-USDT-SWAP": "0.1131",
    "GPS-USDT-SWAP": "0.004845",
    "CRO-USDT-SWAP": "0.09245",
    "UNI-USDT-SWAP": "6.089",
    "STRK-USDT-SWAP": "0.08106",
    "NEIRO-USDT-SWAP": "0.0001088",
    "SUI-USD-SWAP": "1.4444",
    "APE-USDT-SWAP": "0.2049",
    "ENJ-USDT-SWAP": "0.0276",
    "INJ-USDT-SWAP": "4.668",
    "RAY-USDT-SWAP": "0.9264",
    "OL-USDT-SWAP": "0.01701",
    "H-USDT-SWAP": "0.15861",
    "OKB-USDT-SWAP": "107.47",
    "APT-USDT-SWAP": "1.706",
    "WCT-USDT-SWAP": "0.07352",
    "NEO-USDT-SWAP": "3.723",
    "SNX-USDT-SWAP": "0.4282",
    "LIT-USDT-SWAP": "3.401",
    "W-USDT-SWAP": "0.03437",
    "SYRUP-USDT-SWAP": "0.3227",
    "AVAX-USDT-SWAP": "12.67",
    "LPT-USDT-SWAP": "2.884",
    "ACT-USDT-SWAP": "0.03931",
    "FLOKI-USDT-SWAP": "0.00004004",
    "MEME-USDT-SWAP": "0.0009833",
    "DOGE-USDT-SWAP": "0.12433",
    "KGEN-USDT-SWAP": "0.19362",
    "MOODENG-USDT-SWAP": "0.07105",
    "NOT-USDT-SWAP": "0.0005273",
    "AERO-USDT-SWAP": "0.4734",
    "STX-USDT-SWAP": "0.2608",
    "UNI-USD-SWAP": "6.081",
    "ACE-USDT-SWAP": "0.2693",
    "GIGGLE-USDT-SWAP": "67.39",
    "AVAX-USD-SWAP": "12.648",
    "BLUAI-USDT-SWAP": "0.00471",
    "AUCTION-USDT-SWAP": "4.957",
    "WAL-USDT-SWAP": "0.118",
    "FIL-USD-SWAP": "1.338",
    "ETH-USDT-SWAP": "2937.48",
    "SHIB-USDT-SWAP": "0.000007354",
    "ZRO-USDT-SWAP": "1.247",
    "GMX-USDT-SWAP": "8.144",
    "LAYER-USDT-SWAP": "0.1752",
    "ARB-USDT-SWAP": "0.1919",
    "MINA-USDT-SWAP": "0.07994",
    "IMX-USDT-SWAP": "0.2352",
    "LINEA-USDT-SWAP": "0.006669",
    "PUMP-USDT-SWAP": "0.001792",
    "VANA-USDT-SWAP": "2.619",
    "ZBT-USDT-SWAP": "0.16723",
    "XTZ-USDT-SWAP": "0.5065",
    "SUI-USDT-SWAP": "1.4476",
    "ATH-USDT-SWAP": "0.009516",
    "AIXBT-USDT-SWAP": "0.031",
    "PIPPIN-USDT-SWAP": "0.42583",
    "ANIME-USDT-SWAP": "0.007862",
    "PEPE-USDT-SWAP": "0.000004104",
    "LRC-USDT-SWAP": "0.05203",
    "DYDX-USDT-SWAP": "0.1696",
    "LA-USDT-SWAP": "0.2917",
    "JCT-USDT-SWAP": "0.002022",
    "GLM-USDT-SWAP": "0.2008",
    "CHZ-USDT-SWAP": "0.03721",
    "ACH-USDT-SWAP": "0.007799",
    "INIT-USDT-SWAP": "0.0871",
    "PLUME-USDT-SWAP": "0.01735",
    "BCH-USDT-SWAP": "602.8",
    "BLUR-USDT-SWAP": "0.02924",
    "SENT-USDT-SWAP": "0.04774",
    "ALLO-USDT-SWAP": "0.1131",
    "YGG-USDT-SWAP": "0.06527",
    "OM-USDT-SWAP": "0.07349",
    "AAVE-USDT-SWAP": "151.32",
    "METIS-USDT-SWAP": "5.274",
    "ZK-USDT-SWAP": "0.03004",
    "MERL-USDT-SWAP": "0.32643",
    "EGLD-USDT-SWAP": "5.942",
    "AVNT-USDT-SWAP": "0.3717",
    "HMSTR-USDT-SWAP": "0.0002125",
    "AGLD-USDT-SWAP": "0.2603",
    "ONT-USDT-SWAP": "0.07827",
    "ALGO-USDT-SWAP": "0.1204",
    "ADA-USDT-SWAP": "0.3658",
    "TRUMP-USDT-SWAP": "4.943",
    "ME-USDT-SWAP": "0.2041",
    "GALA-USDT-SWAP": "0.006132",
    "BONK-USDT-SWAP": "0.000007869",
    "LUNA-USDT-SWAP": "0.09516",
    "XRP-USD-SWAP": "1.866",
    "ADA-USD-SWAP": "0.3652",
    "TRX-USDT-SWAP": "0.28237",
    "BEAT-USDT-SWAP": "3.00879",
    "XAN-USDT-SWAP": "0.01665",
    "BTC-USD-SWAP": "87649.3",
    "BABY-USDT-SWAP": "0.01683",
    "EDEN-USDT-SWAP": "0.06541",
    "PNUT-USDT-SWAP": "0.06977",
    "BICO-USDT-SWAP": "0.04243",
    "ICP-USDT-SWAP": "2.968",
    "BAND-USDT-SWAP": "0.3264",
    "LDO-USDT-SWAP": "0.5881",
    "SATS-USDT-SWAP": "0.00000001557",
    "ZRX-USDT-SWAP": "0.1404",
    "ZEC-USDT-SWAP": "527.17",
    "MORPHO-USDT-SWAP": "1.1742",
    "QTUM-USDT-SWAP": "1.312",
    "SIGN-USDT-SWAP": "0.03788",
    "TRUTH-USDT-SWAP": "0.010285",
    "YFI-USDT-SWAP": "3391",
    "1INCH-USDT-SWAP": "0.1435",
    "BRETT-USDT-SWAP": "0.01399",
    "SOL-USDT-SWAP": "123.71",
    "ETH-USD-SWAP": "2934.94",
    "FARTCOIN-USDT-SWAP": "0.295",
    "API3-USDT-SWAP": "0.4444",
    "DOT-USDT-SWAP": "1.854",
    "JELLYJELLY-USDT-SWAP": "0.06387",
    "STABLE-USDT-SWAP": "0.0135",
    "F-USDT-SWAP": "0.007293",
    "DOOD-USDT-SWAP": "0.005574",
    "CAT-USDT-SWAP": "0.000002675",
    "COAI-USDT-SWAP": "0.3963",
    "DOGE-USD-SWAP": "0.12421",
    "CATI-USDT-SWAP": "0.0604",
    "WLFI-USDT-SWAP": "0.1433",
    "USDC-USDT-SWAP": "1.0005",
    "IP-USDT-SWAP": "1.629",
    "AT-USDT-SWAP": "0.15876",
    "LINK-USD-SWAP": "12.41",
    "WLD-USDT-SWAP": "0.5023",
    "LQTY-USDT-SWAP": "0.3569",
    "IOTA-USDT-SWAP": "0.08497",
    "TRB-USDT-SWAP": "20.19",
    "RVN-USDT-SWAP": "0.007112",
    "KSM-USDT-SWAP": "7.167",
    "BTC-USD_UM-SWAP": "87704.4",
    "CFX-USDT-SWAP": "0.0716",
    "TREE-USDT-SWAP": "0.1065",
    "SOPH-USDT-SWAP": "0.01275",
    "BARD-USDT-SWAP": "0.7961",
    "UMA-USDT-SWAP": "0.7111",
    "ZEN-USDT-SWAP": "9.094",
    "2Z-USDT-SWAP": "0.1184",
    "YB-USDT-SWAP": "0.4229",
    "RENDER-USDT-SWAP": "1.317",
    "JUP-USDT-SWAP": "0.1929",
    "MAGIC-USDT-SWAP": "0.09615",
    "TURBO-USDT-SWAP": "0.00172",
    "ORDI-USDT-SWAP": "4.16",
    "PYTH-USDT-SWAP": "0.05967",
    "ETC-USDT-SWAP": "12.03",
    "MEW-USDT-SWAP": "0.0008553",
    "CRV-USDT-SWAP": "0.3945",
    "MUBARAK-USDT-SWAP": "0.01594",
    "BIGTIME-USDT-SWAP": "0.02127",
    "ORDER-USDT-SWAP": "0.09499",
    "VIRTUAL-USDT-SWAP": "0.6904",
    "THETA-USDT-SWAP": "0.2723",
    "ONDO-USDT-SWAP": "0.384",
    "LTC-USDT-SWAP": "78.3",
    "SPK-USDT-SWAP": "0.02285",
    "A-USDT-SWAP": "0.158",
    "ASTER-USDT-SWAP": "0.6988",
    "IOST-USDT-SWAP": "0.00166",
    "BTC-USDT-SWAP": "87730.9",
    "BNB-USDT-SWAP": "853.5",
    "SAHARA-USDT-SWAP": "0.02613",
    "MON-USDT-SWAP": "0.02219",
    "PROMPT-USDT-SWAP": "0.04902",
    "RSR-USDT-SWAP": "0.002554",
    "KAITO-USDT-SWAP": "0.5286",
    "LINK-USDT-SWAP": "12.426",
    "NMR-USDT-SWAP": "9.431",
    "XPL-USDT-SWAP": "0.1611",
    "COMP-USDT-SWAP": "25.95",
    "ENA-USDT-SWAP": "0.211",
    "CC-USDT-SWAP": "0.1331",
    "USELESS-USDT-SWAP": "0.06197",
    "RLS-USDT-SWAP": "0.013258",
    "HOME-USDT-SWAP": "0.01689",
    "SOL-USD-SWAP": "123.6",
    "GRT-USDT-SWAP": "0.03652",
    "XAUT-USDT-SWAP": "4336.9",
    "LIGHT-USDT-SWAP": "0.5164",
    "LAB-USDT-SWAP": "0.11063",
    "DOT-USD-SWAP": "1.849",
    "JTO-USDT-SWAP": "0.3953",
    "FIL-USDT-SWAP": "1.34",
    "TIA-USDT-SWAP": "0.4634",
    "SKY-USDT-SWAP": "0.06182",
    "ENS-USDT-SWAP": "9.72",
    "BOME-USDT-SWAP": "0.000565",
    "SOL-USD_UM-SWAP": "123.51",
    "PIEVERSE-USDT-SWAP": "0.5643",
    "0G-USDT-SWAP": "1.0316",
    "GAS-USDT-SWAP": "2.074",
    "SEI-USDT-SWAP": "0.1161",
    "OP-USDT-SWAP": "0.2738",
    "BIO-USDT-SWAP": "0.04533",
    "CORE-USDT-SWAP": "0.1111",
    "MOVE-USDT-SWAP": "0.03546",
    "GRASS-USDT-SWAP": "0.2956",
    "KMNO-USDT-SWAP": "0.05308",
    "SAPIEN-USDT-SWAP": "0.1243",
    "LTC-USD-SWAP": "78.21",
    "TON-USDT-SWAP": "1.663",
    "ATOM-USDT-SWAP": "2.014",
    "ETHW-USDT-SWAP": "0.5316",
    "ONE-USDT-SWAP": "0.003759",
    "SOLV-USDT-SWAP": "0.014594",
    "NIGHT-USDT-SWAP": "0.095904",
    "ETH-USD_UM-SWAP": "2930.73",
    "PENGU-USDT-SWAP": "0.009116",
    "ETHFI-USDT-SWAP": "0.7044",
    "SSV-USDT-SWAP": "3.888",
    "CVX-USDT-SWAP": "1.811",
    "ETC-USD-SWAP": "12.03",
    "RESOLV-USDT-SWAP": "0.07322",
    "MET-USDT-SWAP": "0.2577",
    "SAND-USDT-SWAP": "0.116",
    "CELO-USDT-SWAP": "0.1187",
    "MANA-USDT-SWAP": "0.124",
    "POPCAT-USDT-SWAP": "0.08011",
    "TAO-USDT-SWAP": "222.6",
    "AR-USDT-SWAP": "3.546",
    "FLOW-USDT-SWAP": "0.1122",
    "S-USDT-SWAP": "0.07788",
    "ARKM-USDT-SWAP": "0.187",
    "WET-USDT-SWAP": "0.1779",
    "HUMA-USDT-SWAP": "0.02555",
    "APR-USDT-SWAP": "0.1292",
    "AEVO-USDT-SWAP": "0.03796",
    "BAT-USDT-SWAP": "0.2133",
    "ZORA-USDT-SWAP": "0.04144",
    "BERA-USDT-SWAP": "0.6328",
    "HYPE-USDT-SWAP": "25.963",
    "WOO-USDT-SWAP": "0.02675",
    "PEOPLE-USDT-SWAP": "0.009561",
    "PENDLE-USDT-SWAP": "1.911",
    "SOON-USDT-SWAP": "0.3314",
    "MMT-USDT-SWAP": "0.2316",
    "EIGEN-USDT-SWAP": "0.386",
    "POL-USDT-SWAP": "0.106",
    "PROVE-USDT-SWAP": "0.401",
    "GMT-USDT-SWAP": "0.01804",
    "ZIL-USDT-SWAP": "0.004807",
    "TURTLE-USDT-SWAP": "0.06218",
    "PARTI-USDT-SWAP": "0.1053",
    "MASK-USDT-SWAP": "0.6035",
    "ENSO-USDT-SWAP": "0.7646",
    "BCH-USD-SWAP": "601.8",
    "NEAR-USDT-SWAP": "1.528",
    "COOKIE-USDT-SWAP": "0.03899",
    "SHELL-USDT-SWAP": "0.04964",
    "ZETA-USDT-SWAP": "0.06956",
    "XRP-USDT-SWAP": "1.8672",
    "HBAR-USDT-SWAP": "0.11493",
    "ICX-USDT-SWAP": "0.05658",
    "SPX-USDT-SWAP": "0.4934",
    "AXS-USDT-SWAP": "0.8503"
  }
}