{
  "updated_at": "2026-02-01 22:47:21 UTC",
  "count": 279,
  "source": "OKX SWAP",
  "prices": {
    "MOG-USDT-SWAP": "0.0000001889",
    "WIF-USDT-SWAP": "0.2479",
    "PI-USDT-SWAP": "0.1584",
    "RECALL-USDT-SWAP": "0.06224",
    "SUSHI-USDT-SWAP": "0.2369",
    "RAVE-USDT-SWAP": "0.33107",
    "XLM-USDT-SWAP": "0.17645",
    "DASH-USDT-SWAP": "43.64",
    "TRUST-USDT-SWAP": "0.0837",
    "GPS-USDT-SWAP": "0.006931",
    "CRO-USDT-SWAP": "0.07873",
    "ACU-USDT-SWAP": "0.16699",
    "UNI-USDT-SWAP": "3.876",
    "STRK-USDT-SWAP": "0.05544",
    "NEIRO-USDT-SWAP": "0.0000858",
    "ZKP-USDT-SWAP": "0.0922",
    "SUI-USD-SWAP": "1.1102",
    "APE-USDT-SWAP": "0.1457",
    "ENJ-USDT-SWAP": "0.02406",
    "INJ-USDT-SWAP": "3.554",
    "RAY-USDT-SWAP": "0.715",
    "OL-USDT-SWAP": "0.01431",
    "H-USDT-SWAP": "0.11251",
    "OKB-USDT-SWAP": "88.53",
    "APT-USDT-SWAP": "1.245",
    "WCT-USDT-SWAP": "0.06234",
    "NEO-USDT-SWAP": "3.131",
    "SNX-USDT-SWAP": "0.3428",
    "LIT-USDT-SWAP": "1.517",
    "W-USDT-SWAP": "0.02285",
    "SYRUP-USDT-SWAP": "0.2914",
    "AVAX-USDT-SWAP": "9.988",
    "LPT-USDT-SWAP": "2.57",
    "ACT-USDT-SWAP": "0.01495",
    "FLOKI-USDT-SWAP": "0.00003426",
    "MEME-USDT-SWAP": "0.0008163",
    "DOGE-USDT-SWAP": "0.1048",
    "KGEN-USDT-SWAP": "0.21981",
    "MOODENG-USDT-SWAP": "0.05429",
    "NOT-USDT-SWAP": "0.0004489",
    "AERO-USDT-SWAP": "0.3749",
    "STX-USDT-SWAP": "0.2554",
    "UNI-USD-SWAP": "3.874",
    "ACE-USDT-SWAP": "0.2054",
    "GIGGLE-USDT-SWAP": "36.95",
    "AVAX-USD-SWAP": "9.986",
    "AUCTION-USDT-SWAP": "4.476",
    "WAL-USDT-SWAP": "0.092",
    "FIL-USD-SWAP": "1.048",
    "ETH-USDT-SWAP": "2318.61",
    "SHIB-USDT-SWAP": "0.000006663",
    "ZRO-USDT-SWAP": "1.731",
    "GMX-USDT-SWAP": "6.096",
    "LAYER-USDT-SWAP": "0.1032",
    "ARB-USDT-SWAP": "0.1359",
    "MINA-USDT-SWAP": "0.07153",
    "IMX-USDT-SWAP": "0.1795",
    "LINEA-USDT-SWAP": "0.004463",
    "PUMP-USDT-SWAP": "0.002549",
    "VANA-USDT-SWAP": "1.79",
    "FOGO-USDT-SWAP": "0.03309",
    "ZBT-USDT-SWAP": "0.07613",
    "XTZ-USDT-SWAP": "0.4626",
    "SUI-USDT-SWAP": "1.1118",
    "ATH-USDT-SWAP": "0.006999",
    "AIXBT-USDT-SWAP": "0.02423",
    "PIPPIN-USDT-SWAP": "0.18075",
    "ANIME-USDT-SWAP": "0.005698",
    "PEPE-USDT-SWAP": "0.000004222",
    "LRC-USDT-SWAP": "0.04056",
    "DYDX-USDT-SWAP": "0.1318",
    "LA-USDT-SWAP": "0.2423",
    "GLM-USDT-SWAP": "0.2142",
    "CHZ-USDT-SWAP": "0.04634",
    "ACH-USDT-SWAP": "0.008094",
    "INIT-USDT-SWAP": "0.08411",
    "PLUME-USDT-SWAP": "0.01186",
    "BCH-USDT-SWAP": "523",
    "BLUR-USDT-SWAP": "0.02253",
    "SENT-USDT-SWAP": "0.03539",
    "ALLO-USDT-SWAP": "0.06744",
    "SUI-USD_UM-SWAP": "1.1138",
    "YGG-USDT-SWAP": "0.0461",
    "OM-USDT-SWAP": "0.05052",
    "AAVE-USDT-SWAP": "125.52",
    "METIS-USDT-SWAP": "3.85",
    "ZAMA-USDT-SWAP": "0.04523",
    "ZK-USDT-SWAP": "0.02847",
    "MERL-USDT-SWAP": "0.05509",
    "EGLD-USDT-SWAP": "4.694",
    "AVNT-USDT-SWAP": "0.2391",
    "HMSTR-USDT-SWAP": "0.0001896",
    "AGLD-USDT-SWAP": "0.2337",
    "ONT-USDT-SWAP": "0.0507",
    "ALGO-USDT-SWAP": "0.1014",
    "ADA-USDT-SWAP": "0.2885",
    "TRUMP-USDT-SWAP": "4.158",
    "ME-USDT-SWAP": "0.1601",
    "GALA-USDT-SWAP": "0.004753",
    "BONK-USDT-SWAP": "0.000007066",
    "LUNA-USDT-SWAP": "0.06765",
    "XRP-USD-SWAP": "1.5987",
    "ADA-USD-SWAP": "0.2885",
    "XAG-USDT-SWAP": "83.31",
    "TRX-USDT-SWAP": "0.28508",
    "BEAT-USDT-SWAP": "0.18548",
    "XAN-USDT-SWAP": "0.00889",
    "BTC-USD-SWAP": "77246",
    "BABY-USDT-SWAP": "0.01684",
    "EDEN-USDT-SWAP": "0.04098",
    "PNUT-USDT-SWAP": "0.0568",
    "BICO-USDT-SWAP": "0.02943",
    "PEPE-USD_UM-SWAP": "0.000004179",
    "ICP-USDT-SWAP": "2.644",
    "PUMP-USD_UM-SWAP": "0.00271",
    "BAND-USDT-SWAP": "0.2476",
    "LDO-USDT-SWAP": "0.4118",
    "SATS-USDT-SWAP": "0.00000001252",
    "ZRX-USDT-SWAP": "0.1078",
    "ZEC-USDT-SWAP": "298.41",
    "MORPHO-USDT-SWAP": "1.121",
    "QTUM-USDT-SWAP": "1.077",
    "SPACE-USDT-SWAP": "0.006099",
    "SIGN-USDT-SWAP": "0.0357",
    "TRUTH-USDT-SWAP": "0.01373",
    "YFI-USDT-SWAP": "2804",
    "1INCH-USDT-SWAP": "0.1171",
    "BRETT-USDT-SWAP": "0.00953",
    "SOL-USDT-SWAP": "101.93",
    "RIVER-USDT-SWAP": "11.388",
    "ETH-USD-SWAP": "2316.39",
    "FARTCOIN-USDT-SWAP": "0.2184",
    "API3-USDT-SWAP": "0.3324",
    "DOT-USDT-SWAP": "1.51",
    "JELLYJELLY-USDT-SWAP": "0.05339",
    "STABLE-USDT-SWAP": "0.0247",
    "F-USDT-SWAP": "0.005456",
    "DOOD-USDT-SWAP": "0.004257",
    "CAT-USDT-SWAP": "0.000002094",
    "COAI-USDT-SWAP": "0.2664",
    "DOGE-USD-SWAP": "0.10465",
    "WLFI-USDT-SWAP": "0.1319",
    "USDC-USDT-SWAP": "1.000546",
    "IP-USDT-SWAP": "1.482",
    "AT-USDT-SWAP": "0.1603",
    "LINK-USD-SWAP": "9.547",
    "WLD-USDT-SWAP": "0.3949",
    "LQTY-USDT-SWAP": "0.3178",
    "IOTA-USDT-SWAP": "0.07177",
    "TRB-USDT-SWAP": "16",
    "RVN-USDT-SWAP": "0.006132",
    "DOGE-USD_UM-SWAP": "0.10427",
    "KSM-USDT-SWAP": "5.373",
    "BTC-USD_UM-SWAP": "77395",
    "CFX-USDT-SWAP": "0.05539",
    "SOPH-USDT-SWAP": "0.01084",
    "BARD-USDT-SWAP": "0.6584",
    "UMA-USDT-SWAP": "0.5605",
    "ZEN-USDT-SWAP": "7.014",
    "2Z-USDT-SWAP": "0.1072",
    "YB-USDT-SWAP": "0.1588",
    "RENDER-USDT-SWAP": "1.515",
    "JUP-USDT-SWAP": "0.1748",
    "MAGIC-USDT-SWAP": "0.06814",
    "TURBO-USDT-SWAP": "0.001207",
    "ORDI-USDT-SWAP": "3.106",
    "PYTH-USDT-SWAP": "0.05107",
    "ETC-USDT-SWAP": "9.56",
    "MEW-USDT-SWAP": "0.0007017",
    "CRV-USDT-SWAP": "0.283",
    "MUBARAK-USDT-SWAP": "0.0161",
    "BIGTIME-USDT-SWAP": "0.01741",
    "ORDER-USDT-SWAP": "0.06355",
    "VIRTUAL-USDT-SWAP": "0.6173",
    "THETA-USDT-SWAP": "0.2158",
    "ONDO-USDT-SWAP": "0.278",
    "LTC-USDT-SWAP": "59.01",
    "SPK-USDT-SWAP": "0.02057",
    "ADA-USD_UM-SWAP": "0.3489",
    "A-USDT-SWAP": "0.0918",
    "ASTER-USDT-SWAP": "0.5396",
    "BREV-USDT-SWAP": "0.164",
    "IOST-USDT-SWAP": "0.00139",
    "BTC-USDT-SWAP": "77355.7",
    "BNB-USDT-SWAP": "762.4",
    "SAHARA-USDT-SWAP": "0.01836",
    "MON-USDT-SWAP": "0.01803",
    "PROMPT-USDT-SWAP": "0.05784",
    "RSR-USDT-SWAP": "0.001803",
    "FUN-USDT-SWAP": "0.03659",
    "KAITO-USDT-SWAP": "0.3554",
    "LINK-USDT-SWAP": "9.565",
    "NMR-USDT-SWAP": "8.796",
    "XPL-USDT-SWAP": "0.1024",
    "COMP-USDT-SWAP": "19.26",
    "ENA-USDT-SWAP": "0.1376",
    "CC-USDT-SWAP": "0.1735",
    "USELESS-USDT-SWAP": "0.04337",
    "RLS-USDT-SWAP": "0.006446",
    "HOME-USDT-SWAP": "0.02973",
    "SOL-USD-SWAP": "101.75",
    "GRT-USDT-SWAP": "0.02995",
    "LIGHT-USDT-SWAP": "0.3689",
    "LAB-USDT-SWAP": "0.13469",
    "DOT-USD-SWAP": "1.508",
    "JTO-USDT-SWAP": "0.2866",
    "FIL-USDT-SWAP": "1.05",
    "TIA-USDT-SWAP": "0.3611",
    "SKY-USDT-SWAP": "0.06102",
    "ENS-USDT-SWAP": "6.864",
    "BOME-USDT-SWAP": "0.0004759",
    "SOL-USD_UM-SWAP": "100.93",
    "PIEVERSE-USDT-SWAP": "0.4256",
    "0G-USDT-SWAP": "0.6567",
    "GAS-USDT-SWAP": "1.865",
    "SEI-USDT-SWAP": "0.0853",
    "OP-USDT-SWAP": "0.2297",
    "BIO-USDT-SWAP": "0.03263",
    "CORE-USDT-SWAP": "0.0862",
    "MOVE-USDT-SWAP": "0.02582",
    "GRASS-USDT-SWAP": "0.2122",
    "KMNO-USDT-SWAP": "0.03339",
    "SAPIEN-USDT-SWAP": "0.098",
    "LTC-USD-SWAP": "58.98",
    "TON-USDT-SWAP": "1.334",
    "ATOM-USDT-SWAP": "1.924",
    "ETHW-USDT-SWAP": "0.3929",
    "ONE-USDT-SWAP": "0.002859",
    "XAU-USDT-SWAP": "4818.6",
    "NIGHT-USDT-SWAP": "0.047481",
    "ETH-USD_UM-SWAP": "2317.86",
    "XRP-USD_UM-SWAP": "1.9098",
    "PENGU-USDT-SWAP": "0.007621",
    "ETHFI-USDT-SWAP": "0.4891",
    "SSV-USDT-SWAP": "3.923",
    "CVX-USDT-SWAP": "1.763",
    "ETC-USD-SWAP": "9.55",
    "RESOLV-USDT-SWAP": "0.07959",
    "MET-USDT-SWAP": "0.2304",
    "SAND-USDT-SWAP": "0.1002",
    "CELO-USDT-SWAP": "0.0934",
    "MANA-USDT-SWAP": "0.1129",
    "POPCAT-USDT-SWAP": "0.05547",
    "TAO-USDT-SWAP": "189.9",
    "AR-USDT-SWAP": "2.476",
    "FLOW-USDT-SWAP": "0.05644",
    "S-USDT-SWAP": "0.0503",
    "ARKM-USDT-SWAP": "0.1304",
    "WET-USDT-SWAP": "0.0884",
    "HUMA-USDT-SWAP": "0.02476",
    "APR-USDT-SWAP": "0.08051",
    "AEVO-USDT-SWAP": "0.0286",
    "BAT-USDT-SWAP": "0.1256",
    "ZORA-USDT-SWAP": "0.02687",
    "BERA-USDT-SWAP": "0.46",
    "HYPE-USDT-SWAP": "30.289",
    "WOO-USDT-SWAP": "0.01947",
    "PEOPLE-USDT-SWAP": "0.007475",
    "PENDLE-USDT-SWAP": "1.566",
    "SOON-USDT-SWAP": "0.1953",
    "MMT-USDT-SWAP": "0.1635",
    "EIGEN-USDT-SWAP": "0.2525",
    "POL-USDT-SWAP": "0.1035",
    "PROVE-USDT-SWAP": "0.3329",
    "LTC-USD_UM-SWAP": "59.96",
    "GMT-USDT-SWAP": "0.01358",
    "ZIL-USDT-SWAP": "0.004067",
    "PARTI-USDT-SWAP": "0.07372",
    "MASK-USDT-SWAP": "0.5249",
    "ENSO-USDT-SWAP": "1.2156",
    "BCH-USD-SWAP": "522.5",
    "NEAR-USDT-SWAP": "1.178",
    "SHELL-USDT-SWAP": "0.03711",
    "ZETA-USDT-SWAP": "0.06012",
    "XRP-USDT-SWAP": "1.6011",
    "HBAR-USDT-SWAP": "0.08955",
    "ICX-USDT-SWAP": "0.04475",
    "SPX-USDT-SWAP": "0.2912",
    "AXS-USDT-SWAP": "1.7614"
  }
}