{
  "updated_at": "2026-04-03 22:55:53 UTC",
  "count": 304,
  "source": "OKX SWAP",
  "prices": {
    "XPD-USDT-SWAP": "1502.31",
    "WIF-USDT-SWAP": "0.1817",
    "PI-USDT-SWAP": "0.1711",
    "EDGE-USDT-SWAP": "1.1327",
    "RECALL-USDT-SWAP": "0.04042",
    "SUSHI-USDT-SWAP": "0.1921",
    "RAVE-USDT-SWAP": "0.25558",
    "XLM-USDT-SWAP": "0.16315",
    "DASH-USDT-SWAP": "29.79",
    "TRUST-USDT-SWAP": "0.06495",
    "GPS-USDT-SWAP": "0.007773",
    "CRO-USDT-SWAP": "0.07001",
    "ACU-USDT-SWAP": "0.08207",
    "UNI-USDT-SWAP": "3.158",
    "STRK-USDT-SWAP": "0.03331",
    "NEIRO-USDT-SWAP": "0.00005541",
    "ZKP-USDT-SWAP": "0.0676",
    "SUI-USD-SWAP": "0.8706",
    "APE-USDT-SWAP": "0.08855",
    "MSTR-USDT-SWAP": "120.41",
    "ENJ-USDT-SWAP": "0.01993",
    "INJ-USDT-SWAP": "2.792",
    "RAY-USDT-SWAP": "0.641",
    "OL-USDT-SWAP": "0.00859",
    "H-USDT-SWAP": "0.07929",
    "OKB-USDT-SWAP": "82.48",
    "APT-USDT-SWAP": "0.8461",
    "WCT-USDT-SWAP": "0.05399",
    "NEO-USDT-SWAP": "2.819",
    "SNX-USDT-SWAP": "0.2798",
    "LIT-USDT-SWAP": "0.9828",
    "W-USDT-SWAP": "0.01321",
    "SYRUP-USDT-SWAP": "0.2064",
    "AVAX-USDT-SWAP": "8.907",
    "LPT-USDT-SWAP": "2.016",
    "ACT-USDT-SWAP": "0.01198",
    "FLOKI-USDT-SWAP": "0.0000267",
    "MSFT-USDT-SWAP": "373.03",
    "MEME-USDT-SWAP": "0.0005091",
    "DOGE-USDT-SWAP": "0.09162",
    "KGEN-USDT-SWAP": "0.13768",
    "MOODENG-USDT-SWAP": "0.04505",
    "NOT-USDT-SWAP": "0.0003554",
    "XCU-USDT-SWAP": "5.6549",
    "AERO-USDT-SWAP": "0.3129",
    "STX-USDT-SWAP": "0.2133",
    "UNI-USD-SWAP": "3.158",
    "GIGGLE-USDT-SWAP": "21.4",
    "AVAX-USD-SWAP": "8.898",
    "AUCTION-USDT-SWAP": "4.659",
    "WAL-USDT-SWAP": "0.07118",
    "FIL-USD-SWAP": "0.8377",
    "ETH-USDT-SWAP": "2051.93",
    "SHIB-USDT-SWAP": "0.000005984",
    "ZRO-USDT-SWAP": "1.875",
    "GMX-USDT-SWAP": "5.976",
    "LAYER-USDT-SWAP": "0.07629",
    "ARB-USDT-SWAP": "0.09215",
    "MINA-USDT-SWAP": "0.05653",
    "IMX-USDT-SWAP": "0.1328",
    "LINEA-USDT-SWAP": "0.003057",
    "PUMP-USDT-SWAP": "0.001642",
    "VANA-USDT-SWAP": "1.213",
    "FOGO-USDT-SWAP": "0.01679",
    "BASED-USDT-SWAP": "0.0732",
    "ZBT-USDT-SWAP": "0.09838",
    "XTZ-USDT-SWAP": "0.3494",
    "SUI-USDT-SWAP": "0.8715",
    "ATH-USDT-SWAP": "0.006553",
    "AIXBT-USDT-SWAP": "0.02264",
    "TRIA-USDT-SWAP": "0.02737",
    "PIPPIN-USDT-SWAP": "0.02856",
    "ANIME-USDT-SWAP": "0.004513",
    "PEPE-USDT-SWAP": "0.000003411",
    "LRC-USDT-SWAP": "0.01745",
    "DYDX-USDT-SWAP": "0.10176",
    "LA-USDT-SWAP": "0.1761",
    "GLM-USDT-SWAP": "0.1257",
    "CHZ-USDT-SWAP": "0.03942",
    "ACH-USDT-SWAP": "0.006169",
    "INIT-USDT-SWAP": "0.08254",
    "PLUME-USDT-SWAP": "0.009473",
    "BCH-USDT-SWAP": "443.1",
    "BLUR-USDT-SWAP": "0.01986",
    "SENT-USDT-SWAP": "0.01614",
    "ALLO-USDT-SWAP": "0.10385",
    "XPT-USDT-SWAP": "1996.65",
    "QQQ-USDT-SWAP": "582.5",
    "YGG-USDT-SWAP": "0.03523",
    "AAVE-USDT-SWAP": "94.42",
    "METIS-USDT-SWAP": "2.855",
    "ZAMA-USDT-SWAP": "0.02347",
    "ZK-USDT-SWAP": "0.01554",
    "MERL-USDT-SWAP": "0.02154",
    "EGLD-USDT-SWAP": "3.752",
    "AVNT-USDT-SWAP": "0.1242",
    "HMSTR-USDT-SWAP": "0.0001419",
    "AGLD-USDT-SWAP": "0.2399",
    "ONT-USDT-SWAP": "0.10591",
    "ALGO-USDT-SWAP": "0.12277",
    "ADA-USDT-SWAP": "0.2464",
    "TRUMP-USDT-SWAP": "2.801",
    "ME-USDT-SWAP": "0.10051",
    "NFLX-USDT-SWAP": "97.95",
    "GALA-USDT-SWAP": "0.002909",
    "BONK-USDT-SWAP": "0.000005707",
    "LUNA-USDT-SWAP": "0.05574",
    "XRP-USD-SWAP": "1.3159",
    "ADA-USD-SWAP": "0.2461",
    "XAG-USDT-SWAP": "72.91",
    "TRX-USDT-SWAP": "0.31523",
    "BEAT-USDT-SWAP": "0.36826",
    "BTC-USD-SWAP": "66875.1",
    "BABY-USDT-SWAP": "0.01415",
    "EDEN-USDT-SWAP": "0.0342",
    "PNUT-USDT-SWAP": "0.04052",
    "BICO-USDT-SWAP": "0.02276",
    "ICP-USDT-SWAP": "2.278",
    "META-USDT-SWAP": "574.55",
    "BAND-USDT-SWAP": "0.2097",
    "LDO-USDT-SWAP": "0.3137",
    "SATS-USDT-SWAP": "0.00000001084",
    "ZRX-USDT-SWAP": "0.10281",
    "ZEC-USDT-SWAP": "233.21",
    "MORPHO-USDT-SWAP": "1.4917",
    "QTUM-USDT-SWAP": "0.9645",
    "SPACE-USDT-SWAP": "0.00574",
    "SIGN-USDT-SWAP": "0.03606",
    "AMZN-USDT-SWAP": "208.97",
    "TRUTH-USDT-SWAP": "0.008942",
    "YFI-USDT-SWAP": "2452",
    "1INCH-USDT-SWAP": "0.08681",
    "BRETT-USDT-SWAP": "0.006017",
    "SOL-USDT-SWAP": "80.11",
    "RIVER-USDT-SWAP": "12.134",
    "ETH-USD-SWAP": "2051.44",
    "FARTCOIN-USDT-SWAP": "0.1639",
    "API3-USDT-SWAP": "0.2682",
    "DOT-USDT-SWAP": "1.236",
    "HOOD-USDT-SWAP": "68.71",
    "JELLYJELLY-USDT-SWAP": "0.04163",
    "STABLE-USDT-SWAP": "0.02754",
    "F-USDT-SWAP": "0.0049",
    "DOOD-USDT-SWAP": "0.00289",
    "COAI-USDT-SWAP": "0.2794",
    "DOGE-USD-SWAP": "0.09158",
    "WLFI-USDT-SWAP": "0.09814",
    "USDC-USDT-SWAP": "1.000249",
    "IP-USDT-SWAP": "0.4981",
    "AT-USDT-SWAP": "0.15976",
    "LINK-USD-SWAP": "8.641",
    "WLD-USDT-SWAP": "0.2659",
    "LQTY-USDT-SWAP": "0.2687",
    "IOTA-USDT-SWAP": "0.06375",
    "TRB-USDT-SWAP": "14.59",
    "RVN-USDT-SWAP": "0.005676",
    "ORCL-USDT-SWAP": "145.5",
    "KSM-USDT-SWAP": "4.189",
    "BTC-USD_UM-SWAP": "66831.4",
    "CFX-USDT-SWAP": "0.052",
    "SOPH-USDT-SWAP": "0.008179",
    "BARD-USDT-SWAP": "0.2972",
    "UMA-USDT-SWAP": "0.4014",
    "ZEN-USDT-SWAP": "5.148",
    "2Z-USDT-SWAP": "0.07561",
    "YB-USDT-SWAP": "0.12785",
    "CRCL-USDT-SWAP": "90.68",
    "RENDER-USDT-SWAP": "1.925",
    "JUP-USDT-SWAP": "0.1626",
    "MAGIC-USDT-SWAP": "0.05936",
    "TURBO-USDT-SWAP": "0.0009964",
    "ORDI-USDT-SWAP": "2.473",
    "PYTH-USDT-SWAP": "0.0407",
    "ETC-USDT-SWAP": "8.071",
    "MEW-USDT-SWAP": "0.0005492",
    "CRV-USDT-SWAP": "0.2092",
    "MUBARAK-USDT-SWAP": "0.01109",
    "BIGTIME-USDT-SWAP": "0.01212",
    "ORDER-USDT-SWAP": "0.0487",
    "VIRTUAL-USDT-SWAP": "0.6358",
    "INTC-USDT-SWAP": "50.15",
    "THETA-USDT-SWAP": "0.1456",
    "ONDO-USDT-SWAP": "0.2599",
    "LTC-USDT-SWAP": "53.22",
    "SPK-USDT-SWAP": "0.02017",
    "A-USDT-SWAP": "0.07949",
    "ROBO-USDT-SWAP": "0.01847",
    "EWJ-USDT-SWAP": "85.35",
    "ASTER-USDT-SWAP": "0.6521",
    "BREV-USDT-SWAP": "0.1087",
    "IOST-USDT-SWAP": "0.001086",
    "BTC-USDT-SWAP": "66876",
    "EWY-USDT-SWAP": "122.02",
    "BNB-USDT-SWAP": "586.9",
    "SAHARA-USDT-SWAP": "0.02076",
    "MON-USDT-SWAP": "0.02726",
    "AAPL-USDT-SWAP": "254.83",
    "RSR-USDT-SWAP": "0.00144",
    "SPY-USDT-SWAP": "651.24",
    "KAITO-USDT-SWAP": "0.414",
    "LINK-USDT-SWAP": "8.653",
    "NMR-USDT-SWAP": "7.17",
    "TSLA-USDT-SWAP": "361",
    "XPL-USDT-SWAP": "0.10977",
    "COMP-USDT-SWAP": "16.94",
    "ENA-USDT-SWAP": "0.0791",
    "CC-USDT-SWAP": "0.13836",
    "USELESS-USDT-SWAP": "0.03476",
    "PLTR-USDT-SWAP": "147.86",
    "RLS-USDT-SWAP": "0.002385",
    "HOME-USDT-SWAP": "0.02",
    "SOL-USD-SWAP": "80.1",
    "GRT-USDT-SWAP": "0.0239",
    "LIGHT-USDT-SWAP": "0.1597",
    "KAT-USDT-SWAP": "0.00879",
    "LAB-USDT-SWAP": "0.20208",
    "DOT-USD-SWAP": "1.235",
    "JTO-USDT-SWAP": "0.2558",
    "FIL-USDT-SWAP": "0.8378",
    "TIA-USDT-SWAP": "0.2896",
    "MU-USDT-SWAP": "363.66",
    "SKY-USDT-SWAP": "0.07451",
    "ENS-USDT-SWAP": "5.505",
    "NVDA-USDT-SWAP": "176.25",
    "BOME-USDT-SWAP": "0.0003849",
    "SOL-USD_UM-SWAP": "80.03",
    "PIEVERSE-USDT-SWAP": "0.5342",
    "XAU-USD_UM-SWAP": "4654.1",
    "0G-USDT-SWAP": "0.5236",
    "GAS-USDT-SWAP": "1.813",
    "SEI-USDT-SWAP": "0.05433",
    "OP-USDT-SWAP": "0.1102",
    "AMD-USDT-SWAP": "215.62",
    "BIO-USDT-SWAP": "0.01707",
    "CORE-USDT-SWAP": "0.02474",
    "MOVE-USDT-SWAP": "0.01751",
    "NG-USDT-SWAP": "2.8144",
    "GRASS-USDT-SWAP": "0.2768",
    "KMNO-USDT-SWAP": "0.01743",
    "SAPIEN-USDT-SWAP": "0.06917",
    "OPN-USDT-SWAP": "0.1807",
    "LTC-USD-SWAP": "53.18",
    "TON-USDT-SWAP": "1.24",
    "ATOM-USDT-SWAP": "1.691",
    "ETHW-USDT-SWAP": "0.2502",
    "ONE-USDT-SWAP": "0.002268",
    "COIN-USDT-SWAP": "171.54",
    "ESP-USDT-SWAP": "0.07504",
    "XAU-USDT-SWAP": "4653",
    "NIGHT-USDT-SWAP": "0.043953",
    "ETH-USD_UM-SWAP": "2050.26",
    "BSB-USDT-SWAP": "0.2264",
    "PENGU-USDT-SWAP": "0.006272",
    "ETHFI-USDT-SWAP": "0.4387",
    "SSV-USDT-SWAP": "2.26",
    "CVX-USDT-SWAP": "1.703",
    "ETC-USD-SWAP": "8.063",
    "RESOLV-USDT-SWAP": "0.03864",
    "MET-USDT-SWAP": "0.128",
    "SAND-USDT-SWAP": "0.0767",
    "CELO-USDT-SWAP": "0.08418",
    "SNDK-USDT-SWAP": "690.6",
    "MANA-USDT-SWAP": "0.08646",
    "POPCAT-USDT-SWAP": "0.04791",
    "TAO-USDT-SWAP": "307.6",
    "AR-USDT-SWAP": "1.682",
    "FLOW-USDT-SWAP": "0.02989",
    "S-USDT-SWAP": "0.04194",
    "AZTEC-USDT-SWAP": "0.01859",
    "ARKM-USDT-SWAP": "0.09581",
    "WET-USDT-SWAP": "0.10498",
    "HUMA-USDT-SWAP": "0.01464",
    "APR-USDT-SWAP": "0.17752",
    "AEVO-USDT-SWAP": "0.02266",
    "CL-USDT-SWAP": "111.67",
    "BAT-USDT-SWAP": "0.0955",
    "ZORA-USDT-SWAP": "0.01376",
    "BERA-USDT-SWAP": "0.4009",
    "TSM-USDT-SWAP": "336.31",
    "HYPE-USDT-SWAP": "35.653",
    "WOO-USDT-SWAP": "0.01686",
    "PEOPLE-USDT-SWAP": "0.006536",
    "PENDLE-USDT-SWAP": "1.058",
    "SOON-USDT-SWAP": "0.1159",
    "MMT-USDT-SWAP": "0.1101",
    "EIGEN-USDT-SWAP": "0.1508",
    "POL-USDT-SWAP": "0.09221",
    "PROVE-USDT-SWAP": "0.2208",
    "GMT-USDT-SWAP": "0.010096",
    "ZIL-USDT-SWAP": "0.003888",
    "PARTI-USDT-SWAP": "0.08592",
    "MASK-USDT-SWAP": "0.4508",
    "ENSO-USDT-SWAP": "0.9164",
    "BCH-USD-SWAP": "443",
    "BZ-USDT-SWAP": "109.76",
    "NEAR-USDT-SWAP": "1.206",
    "SHELL-USDT-SWAP": "0.02972",
    "ZETA-USDT-SWAP": "0.04688",
    "GOOGL-USDT-SWAP": "294.9",
    "XRP-USDT-SWAP": "1.3167",
    "HBAR-USDT-SWAP": "0.08765",
    "ICX-USDT-SWAP": "0.03816",
    "SPX-USDT-SWAP": "0.2641",
    "AXS-USDT-SWAP": "1.1115"
  }
}