{
  "updated_at": "2026-01-27 20:43:46 UTC",
  "count": 271,
  "source": "OKX SWAP",
  "prices": {
    "MOG-USDT-SWAP": "0.0000002453",
    "WIF-USDT-SWAP": "0.3305",
    "PI-USDT-SWAP": "0.1752",
    "RECALL-USDT-SWAP": "0.08052",
    "SUSHI-USDT-SWAP": "0.301",
    "RAVE-USDT-SWAP": "0.34837",
    "XLM-USDT-SWAP": "0.20796",
    "DASH-USDT-SWAP": "64.34",
    "TRUST-USDT-SWAP": "0.10719",
    "GPS-USDT-SWAP": "0.007408",
    "CRO-USDT-SWAP": "0.09086",
    "ACU-USDT-SWAP": "0.21458",
    "UNI-USDT-SWAP": "4.776",
    "STRK-USDT-SWAP": "0.06988",
    "NEIRO-USDT-SWAP": "0.0001153",
    "ZKP-USDT-SWAP": "0.1138",
    "SUI-USD-SWAP": "1.444",
    "APE-USDT-SWAP": "0.1839",
    "ENJ-USDT-SWAP": "0.02788",
    "INJ-USDT-SWAP": "4.479",
    "RAY-USDT-SWAP": "0.9866",
    "OL-USDT-SWAP": "0.01798",
    "H-USDT-SWAP": "0.15817",
    "OKB-USDT-SWAP": "106.2",
    "APT-USDT-SWAP": "1.575",
    "WCT-USDT-SWAP": "0.07738",
    "NEO-USDT-SWAP": "3.584",
    "SNX-USDT-SWAP": "0.4156",
    "LIT-USDT-SWAP": "1.913",
    "W-USDT-SWAP": "0.02904",
    "SYRUP-USDT-SWAP": "0.3408",
    "AVAX-USDT-SWAP": "11.967",
    "LPT-USDT-SWAP": "3.215",
    "ACT-USDT-SWAP": "0.02211",
    "FLOKI-USDT-SWAP": "0.00004219",
    "MEME-USDT-SWAP": "0.0010537",
    "DOGE-USDT-SWAP": "0.12504",
    "KGEN-USDT-SWAP": "0.28023",
    "MOODENG-USDT-SWAP": "0.06872",
    "NOT-USDT-SWAP": "0.0005489",
    "AERO-USDT-SWAP": "0.4608",
    "STX-USDT-SWAP": "0.3026",
    "UNI-USD-SWAP": "4.768",
    "ACE-USDT-SWAP": "0.2448",
    "GIGGLE-USDT-SWAP": "48.66",
    "AVAX-USD-SWAP": "11.953",
    "AUCTION-USDT-SWAP": "6.101",
    "WAL-USDT-SWAP": "0.1217",
    "FIL-USD-SWAP": "1.276",
    "ETH-USDT-SWAP": "3001.19",
    "SHIB-USDT-SWAP": "0.000007822",
    "ZRO-USDT-SWAP": "2.013",
    "GMX-USDT-SWAP": "7.474",
    "LAYER-USDT-SWAP": "0.1385",
    "ARB-USDT-SWAP": "0.1715",
    "MINA-USDT-SWAP": "0.08891",
    "IMX-USDT-SWAP": "0.2357",
    "LINEA-USDT-SWAP": "0.006432",
    "PUMP-USDT-SWAP": "0.003126",
    "VANA-USDT-SWAP": "2.096",
    "FOGO-USDT-SWAP": "0.03812",
    "ZBT-USDT-SWAP": "0.09262",
    "XTZ-USDT-SWAP": "0.5719",
    "SUI-USDT-SWAP": "1.4475",
    "ATH-USDT-SWAP": "0.009018",
    "AIXBT-USDT-SWAP": "0.03061",
    "PIPPIN-USDT-SWAP": "0.4441",
    "ANIME-USDT-SWAP": "0.006744",
    "PEPE-USDT-SWAP": "0.000005037",
    "LRC-USDT-SWAP": "0.04764",
    "DYDX-USDT-SWAP": "0.1716",
    "LA-USDT-SWAP": "0.305",
    "GLM-USDT-SWAP": "0.2431",
    "CHZ-USDT-SWAP": "0.05734",
    "ACH-USDT-SWAP": "0.01045",
    "INIT-USDT-SWAP": "0.09237",
    "PLUME-USDT-SWAP": "0.01532",
    "BCH-USDT-SWAP": "597.5",
    "BLUR-USDT-SWAP": "0.02929",
    "SENT-USDT-SWAP": "0.02623",
    "ALLO-USDT-SWAP": "0.08979",
    "YGG-USDT-SWAP": "0.06318",
    "OM-USDT-SWAP": "0.06482",
    "AAVE-USDT-SWAP": "157.91",
    "METIS-USDT-SWAP": "4.735",
    "ZAMA-USDT-SWAP": "0.04753",
    "ZK-USDT-SWAP": "0.02793",
    "MERL-USDT-SWAP": "0.08457",
    "EGLD-USDT-SWAP": "5.758",
    "AVNT-USDT-SWAP": "0.2961",
    "HMSTR-USDT-SWAP": "0.0002329",
    "AGLD-USDT-SWAP": "0.2814",
    "ONT-USDT-SWAP": "0.05952",
    "ALGO-USDT-SWAP": "0.121",
    "ADA-USDT-SWAP": "0.3593",
    "TRUMP-USDT-SWAP": "4.802",
    "ME-USDT-SWAP": "0.2065",
    "GALA-USDT-SWAP": "0.006119",
    "BONK-USDT-SWAP": "0.000008779",
    "LUNA-USDT-SWAP": "0.07901",
    "XRP-USD-SWAP": "1.9128",
    "ADA-USD-SWAP": "0.3585",
    "TRX-USDT-SWAP": "0.2946",
    "BEAT-USDT-SWAP": "0.2747",
    "XAN-USDT-SWAP": "0.01137",
    "BTC-USD-SWAP": "88787.6",
    "BABY-USDT-SWAP": "0.01802",
    "EDEN-USDT-SWAP": "0.05596",
    "PNUT-USDT-SWAP": "0.07277",
    "BICO-USDT-SWAP": "0.03835",
    "ICP-USDT-SWAP": "3.331",
    "BAND-USDT-SWAP": "0.2865",
    "LDO-USDT-SWAP": "0.5246",
    "SATS-USDT-SWAP": "0.00000001568",
    "ZRX-USDT-SWAP": "0.1316",
    "ZEC-USDT-SWAP": "398.17",
    "MORPHO-USDT-SWAP": "1.205",
    "QTUM-USDT-SWAP": "1.27",
    "SPACE-USDT-SWAP": "0.011837",
    "SIGN-USDT-SWAP": "0.03856",
    "TRUTH-USDT-SWAP": "0.013525",
    "YFI-USDT-SWAP": "3388",
    "1INCH-USDT-SWAP": "0.1188",
    "BRETT-USDT-SWAP": "0.01324",
    "SOL-USDT-SWAP": "126.68",
    "RIVER-USDT-SWAP": "61.269",
    "ETH-USD-SWAP": "2998.27",
    "FARTCOIN-USDT-SWAP": "0.307",
    "API3-USDT-SWAP": "0.4048",
    "DOT-USDT-SWAP": "1.883",
    "JELLYJELLY-USDT-SWAP": "0.06063",
    "STABLE-USDT-SWAP": "0.02253",
    "F-USDT-SWAP": "0.006698",
    "DOOD-USDT-SWAP": "0.004974",
    "CAT-USDT-SWAP": "0.000002635",
    "COAI-USDT-SWAP": "0.376",
    "DOGE-USD-SWAP": "0.12486",
    "WLFI-USDT-SWAP": "0.1591",
    "USDC-USDT-SWAP": "1.000818",
    "IP-USDT-SWAP": "2.187",
    "AT-USDT-SWAP": "0.15992",
    "LINK-USD-SWAP": "12.021",
    "WLD-USDT-SWAP": "0.4649",
    "LQTY-USDT-SWAP": "0.3421",
    "IOTA-USDT-SWAP": "0.08759",
    "TRB-USDT-SWAP": "19.57",
    "RVN-USDT-SWAP": "0.007205",
    "KSM-USDT-SWAP": "6.807",
    "BTC-USD_UM-SWAP": "88737.8",
    "CFX-USDT-SWAP": "0.06838",
    "SOPH-USDT-SWAP": "0.01248",
    "BARD-USDT-SWAP": "0.7703",
    "UMA-USDT-SWAP": "0.6877",
    "ZEN-USDT-SWAP": "9.638",
    "2Z-USDT-SWAP": "0.1189",
    "YB-USDT-SWAP": "0.248",
    "RENDER-USDT-SWAP": "1.859",
    "JUP-USDT-SWAP": "0.2027",
    "MAGIC-USDT-SWAP": "0.09002",
    "TURBO-USDT-SWAP": "0.001517",
    "ORDI-USDT-SWAP": "3.953",
    "PYTH-USDT-SWAP": "0.06318",
    "ETC-USDT-SWAP": "11.54",
    "MEW-USDT-SWAP": "0.0009031",
    "CRV-USDT-SWAP": "0.3459",
    "MUBARAK-USDT-SWAP": "0.01825",
    "BIGTIME-USDT-SWAP": "0.0213",
    "ORDER-USDT-SWAP": "0.08084",
    "VIRTUAL-USDT-SWAP": "0.823",
    "THETA-USDT-SWAP": "0.2712",
    "ONDO-USDT-SWAP": "0.3366",
    "LTC-USDT-SWAP": "69.9",
    "SPK-USDT-SWAP": "0.02275",
    "A-USDT-SWAP": "0.1102",
    "ASTER-USDT-SWAP": "0.6559",
    "BREV-USDT-SWAP": "0.2233",
    "IOST-USDT-SWAP": "0.001541",
    "BTC-USDT-SWAP": "88894.9",
    "BNB-USDT-SWAP": "894.7",
    "SAHARA-USDT-SWAP": "0.02413",
    "MON-USDT-SWAP": "0.02154",
    "PROMPT-USDT-SWAP": "0.06818",
    "RSR-USDT-SWAP": "0.002357",
    "FUN-USDT-SWAP": "0.06169",
    "KAITO-USDT-SWAP": "0.42",
    "LINK-USDT-SWAP": "12.053",
    "NMR-USDT-SWAP": "9.333",
    "XPL-USDT-SWAP": "0.1364",
    "COMP-USDT-SWAP": "23.89",
    "ENA-USDT-SWAP": "0.1732",
    "CC-USDT-SWAP": "0.15269",
    "USELESS-USDT-SWAP": "0.06376",
    "RLS-USDT-SWAP": "0.008023",
    "HOME-USDT-SWAP": "0.031",
    "SOL-USD-SWAP": "126.47",
    "GRT-USDT-SWAP": "0.03676",
    "LIGHT-USDT-SWAP": "0.4172",
    "LAB-USDT-SWAP": "0.16023",
    "DOT-USD-SWAP": "1.879",
    "JTO-USDT-SWAP": "0.3543",
    "FIL-USDT-SWAP": "1.279",
    "TIA-USDT-SWAP": "0.4538",
    "SKY-USDT-SWAP": "0.06328",
    "ENS-USDT-SWAP": "9.1",
    "BOME-USDT-SWAP": "0.0005882",
    "SOL-USD_UM-SWAP": "126.77",
    "PIEVERSE-USDT-SWAP": "0.6012",
    "0G-USDT-SWAP": "0.8445",
    "GAS-USDT-SWAP": "1.966",
    "SEI-USDT-SWAP": "0.1071",
    "OP-USDT-SWAP": "0.3012",
    "BIO-USDT-SWAP": "0.04519",
    "CORE-USDT-SWAP": "0.1091",
    "MOVE-USDT-SWAP": "0.03382",
    "GRASS-USDT-SWAP": "0.264",
    "KMNO-USDT-SWAP": "0.03908",
    "SAPIEN-USDT-SWAP": "0.1215",
    "LTC-USD-SWAP": "69.8",
    "TON-USDT-SWAP": "1.525",
    "ATOM-USDT-SWAP": "2.251",
    "ETHW-USDT-SWAP": "0.4829",
    "ONE-USDT-SWAP": "0.00353",
    "XAU-USDT-SWAP": "5150.7",
    "NIGHT-USDT-SWAP": "0.061092",
    "ETH-USD_UM-SWAP": "2995.32",
    "PENGU-USDT-SWAP": "0.009846",
    "ETHFI-USDT-SWAP": "0.6289",
    "SSV-USDT-SWAP": "4.18",
    "CVX-USDT-SWAP": "2.09",
    "ETC-USD-SWAP": "11.53",
    "RESOLV-USDT-SWAP": "0.12683",
    "MET-USDT-SWAP": "0.2603",
    "SAND-USDT-SWAP": "0.1285",
    "CELO-USDT-SWAP": "0.1201",
    "MANA-USDT-SWAP": "0.1403",
    "POPCAT-USDT-SWAP": "0.07386",
    "TAO-USDT-SWAP": "235.4",
    "AR-USDT-SWAP": "3.366",
    "FLOW-USDT-SWAP": "0.0748",
    "S-USDT-SWAP": "0.0674",
    "ARKM-USDT-SWAP": "0.1679",
    "WET-USDT-SWAP": "0.119",
    "HUMA-USDT-SWAP": "0.02481",
    "APR-USDT-SWAP": "0.10911",
    "AEVO-USDT-SWAP": "0.03647",
    "BAT-USDT-SWAP": "0.1759",
    "ZORA-USDT-SWAP": "0.03106",
    "BERA-USDT-SWAP": "0.646",
    "HYPE-USDT-SWAP": "29.373",
    "WOO-USDT-SWAP": "0.02499",
    "PEOPLE-USDT-SWAP": "0.009343",
    "PENDLE-USDT-SWAP": "1.898",
    "SOON-USDT-SWAP": "0.2997",
    "MMT-USDT-SWAP": "0.2111",
    "EIGEN-USDT-SWAP": "0.3324",
    "POL-USDT-SWAP": "0.1199",
    "PROVE-USDT-SWAP": "0.3688",
    "GMT-USDT-SWAP": "0.01609",
    "ZIL-USDT-SWAP": "0.004938",
    "PARTI-USDT-SWAP": "0.08743",
    "MASK-USDT-SWAP": "0.643",
    "ENSO-USDT-SWAP": "1.3329",
    "BCH-USD-SWAP": "596.6",
    "NEAR-USDT-SWAP": "1.492",
    "SHELL-USDT-SWAP": "0.0455",
    "ZETA-USDT-SWAP": "0.07362",
    "XRP-USDT-SWAP": "1.9157",
    "HBAR-USDT-SWAP": "0.10762",
    "ICX-USDT-SWAP": "0.054",
    "SPX-USDT-SWAP": "0.3899",
    "AXS-USDT-SWAP": "2.4995"
  }
}