{
  "updated_at": "2026-01-11 03:17:32 UTC",
  "count": 275,
  "source": "OKX SWAP",
  "prices": {
    "MOG-USDT-SWAP": "0.00000033",
    "WIF-USDT-SWAP": "0.3823",
    "PI-USDT-SWAP": "0.2089",
    "RECALL-USDT-SWAP": "0.10722",
    "SUSHI-USDT-SWAP": "0.3235",
    "RAVE-USDT-SWAP": "0.32",
    "XLM-USDT-SWAP": "0.22702",
    "DASH-USDT-SWAP": "37.42",
    "TRUST-USDT-SWAP": "0.1157",
    "GPS-USDT-SWAP": "0.006431",
    "CRO-USDT-SWAP": "0.10079",
    "UNI-USDT-SWAP": "5.51",
    "STRK-USDT-SWAP": "0.08188",
    "NEIRO-USDT-SWAP": "0.0001321",
    "ZKP-USDT-SWAP": "0.1451",
    "SUI-USD-SWAP": "1.7967",
    "APE-USDT-SWAP": "0.2128",
    "ENJ-USDT-SWAP": "0.03075",
    "INJ-USDT-SWAP": "5.201",
    "RAY-USDT-SWAP": "1.1738",
    "OL-USDT-SWAP": "0.01883",
    "H-USDT-SWAP": "0.16848",
    "OKB-USDT-SWAP": "110.23",
    "APT-USDT-SWAP": "1.814",
    "WCT-USDT-SWAP": "0.07929",
    "NEO-USDT-SWAP": "3.937",
    "SNX-USDT-SWAP": "0.4741",
    "LIT-USDT-SWAP": "2.645",
    "W-USDT-SWAP": "0.03695",
    "SYRUP-USDT-SWAP": "0.395",
    "AVAX-USDT-SWAP": "13.697",
    "LPT-USDT-SWAP": "3.204",
    "ACT-USDT-SWAP": "0.02594",
    "FLOKI-USDT-SWAP": "0.00005173",
    "MEME-USDT-SWAP": "0.0011593",
    "DOGE-USDT-SWAP": "0.13896",
    "KGEN-USDT-SWAP": "0.20171",
    "MOODENG-USDT-SWAP": "0.08077",
    "NOT-USDT-SWAP": "0.0005901",
    "AERO-USDT-SWAP": "0.5398",
    "STX-USDT-SWAP": "0.3832",
    "UNI-USD-SWAP": "5.503",
    "ACE-USDT-SWAP": "0.2865",
    "GIGGLE-USDT-SWAP": "66.74",
    "AVAX-USD-SWAP": "13.677",
    "BLUAI-USDT-SWAP": "0.004906",
    "AUCTION-USDT-SWAP": "5.469",
    "WAL-USDT-SWAP": "0.1419",
    "FIL-USD-SWAP": "1.484",
    "ETH-USDT-SWAP": "3092.67",
    "SHIB-USDT-SWAP": "0.00000865",
    "ZRO-USDT-SWAP": "1.476",
    "GMX-USDT-SWAP": "7.998",
    "LAYER-USDT-SWAP": "0.1705",
    "ARB-USDT-SWAP": "0.2071",
    "MINA-USDT-SWAP": "0.08504",
    "IMX-USDT-SWAP": "0.269",
    "LINEA-USDT-SWAP": "0.00676",
    "PUMP-USDT-SWAP": "0.0023",
    "VANA-USDT-SWAP": "2.357",
    "FOGO-USDT-SWAP": "0.06575",
    "ZBT-USDT-SWAP": "0.12182",
    "XTZ-USDT-SWAP": "0.5807",
    "SUI-USDT-SWAP": "1.7991",
    "ATH-USDT-SWAP": "0.01033",
    "AIXBT-USDT-SWAP": "0.03688",
    "PIPPIN-USDT-SWAP": "0.34367",
    "ANIME-USDT-SWAP": "0.007339",
    "PEPE-USDT-SWAP": "0.000005971",
    "LRC-USDT-SWAP": "0.052",
    "DYDX-USDT-SWAP": "0.2032",
    "LA-USDT-SWAP": "0.313",
    "JCT-USDT-SWAP": "0.002075",
    "GLM-USDT-SWAP": "0.2903",
    "CHZ-USDT-SWAP": "0.0493",
    "ACH-USDT-SWAP": "0.010098",
    "INIT-USDT-SWAP": "0.09583",
    "PLUME-USDT-SWAP": "0.01748",
    "BCH-USDT-SWAP": "646.4",
    "BLUR-USDT-SWAP": "0.03179",
    "SENT-USDT-SWAP": "0.04644",
    "ALLO-USDT-SWAP": "0.1112",
    "YGG-USDT-SWAP": "0.06865",
    "OM-USDT-SWAP": "0.0786",
    "AAVE-USDT-SWAP": "165.06",
    "METIS-USDT-SWAP": "4.96",
    "ZAMA-USDT-SWAP": "0.1061",
    "ZK-USDT-SWAP": "0.0341",
    "MERL-USDT-SWAP": "0.25246",
    "EGLD-USDT-SWAP": "6.294",
    "AVNT-USDT-SWAP": "0.3236",
    "HMSTR-USDT-SWAP": "0.0002507",
    "AGLD-USDT-SWAP": "0.2846",
    "ONT-USDT-SWAP": "0.06308",
    "ALGO-USDT-SWAP": "0.1338",
    "ADA-USDT-SWAP": "0.3897",
    "TRUMP-USDT-SWAP": "5.389",
    "ME-USDT-SWAP": "0.2155",
    "GALA-USDT-SWAP": "0.007101",
    "BONK-USDT-SWAP": "0.000010557",
    "LUNA-USDT-SWAP": "0.09076",
    "XRP-USD-SWAP": "2.0896",
    "ADA-USD-SWAP": "0.389",
    "TRX-USDT-SWAP": "0.29908",
    "BEAT-USDT-SWAP": "0.44866",
    "XAN-USDT-SWAP": "0.01715",
    "BTC-USD-SWAP": "90493.6",
    "BABY-USDT-SWAP": "0.01818",
    "EDEN-USDT-SWAP": "0.07311",
    "PNUT-USDT-SWAP": "0.08443",
    "BICO-USDT-SWAP": "0.04544",
    "ICP-USDT-SWAP": "3.182",
    "BAND-USDT-SWAP": "0.3419",
    "LDO-USDT-SWAP": "0.6334",
    "SATS-USDT-SWAP": "0.00000001702",
    "ZRX-USDT-SWAP": "0.1406",
    "ZEC-USDT-SWAP": "380.33",
    "MORPHO-USDT-SWAP": "1.2984",
    "QTUM-USDT-SWAP": "1.49",
    "SIGN-USDT-SWAP": "0.03947",
    "TRUTH-USDT-SWAP": "0.011759",
    "YFI-USDT-SWAP": "3438",
    "1INCH-USDT-SWAP": "0.1559",
    "BRETT-USDT-SWAP": "0.01779",
    "SOL-USDT-SWAP": "135.92",
    "RIVER-USDT-SWAP": "14.561",
    "ETH-USD-SWAP": "3089.01",
    "FARTCOIN-USDT-SWAP": "0.376",
    "API3-USDT-SWAP": "0.4551",
    "DOT-USDT-SWAP": "2.094",
    "JELLYJELLY-USDT-SWAP": "0.06625",
    "STABLE-USDT-SWAP": "0.01435",
    "F-USDT-SWAP": "0.00697",
    "DOOD-USDT-SWAP": "0.005536",
    "CAT-USDT-SWAP": "0.000003133",
    "COAI-USDT-SWAP": "0.4196",
    "DOGE-USD-SWAP": "0.13877",
    "CATI-USDT-SWAP": "0.0601",
    "WLFI-USDT-SWAP": "0.1678",
    "USDC-USDT-SWAP": "1.000499",
    "IP-USDT-SWAP": "2.004",
    "AT-USDT-SWAP": "0.16247",
    "LINK-USD-SWAP": "13.166",
    "WLD-USDT-SWAP": "0.5725",
    "LQTY-USDT-SWAP": "0.4027",
    "IOTA-USDT-SWAP": "0.1013",
    "TRB-USDT-SWAP": "21.55",
    "RVN-USDT-SWAP": "0.00767",
    "KSM-USDT-SWAP": "7.787",
    "BTC-USD_UM-SWAP": "90437.8",
    "CFX-USDT-SWAP": "0.07694",
    "TREE-USDT-SWAP": "0.1102",
    "SOPH-USDT-SWAP": "0.01272",
    "BARD-USDT-SWAP": "0.7896",
    "UMA-USDT-SWAP": "0.7613",
    "ZEN-USDT-SWAP": "8.466",
    "2Z-USDT-SWAP": "0.1156",
    "YB-USDT-SWAP": "0.4357",
    "RENDER-USDT-SWAP": "2.336",
    "JUP-USDT-SWAP": "0.2106",
    "MAGIC-USDT-SWAP": "0.1",
    "TURBO-USDT-SWAP": "0.001918",
    "ORDI-USDT-SWAP": "4.55",
    "PYTH-USDT-SWAP": "0.06785",
    "ETC-USDT-SWAP": "12.52",
    "MEW-USDT-SWAP": "0.0010063",
    "CRV-USDT-SWAP": "0.4075",
    "MUBARAK-USDT-SWAP": "0.02193",
    "BIGTIME-USDT-SWAP": "0.02218",
    "ORDER-USDT-SWAP": "0.10285",
    "VIRTUAL-USDT-SWAP": "1.0578",
    "THETA-USDT-SWAP": "0.301",
    "ONDO-USDT-SWAP": "0.3999",
    "LTC-USDT-SWAP": "81.46",
    "SPK-USDT-SWAP": "0.02425",
    "A-USDT-SWAP": "0.1779",
    "ASTER-USDT-SWAP": "0.7202",
    "BREV-USDT-SWAP": "0.3691",
    "IOST-USDT-SWAP": "0.001703",
    "BTC-USDT-SWAP": "90597.2",
    "BNB-USDT-SWAP": "910.1",
    "SAHARA-USDT-SWAP": "0.02898",
    "MON-USDT-SWAP": "0.02427",
    "PROMPT-USDT-SWAP": "0.05861",
    "RSR-USDT-SWAP": "0.002693",
    "KAITO-USDT-SWAP": "0.5967",
    "LINK-USDT-SWAP": "13.186",
    "NMR-USDT-SWAP": "9.997",
    "XPL-USDT-SWAP": "0.1641",
    "COMP-USDT-SWAP": "26.36",
    "ENA-USDT-SWAP": "0.2282",
    "CC-USDT-SWAP": "0.12958",
    "USELESS-USDT-SWAP": "0.10207",
    "RLS-USDT-SWAP": "0.010955",
    "HOME-USDT-SWAP": "0.02598",
    "SOL-USD-SWAP": "135.77",
    "GRT-USDT-SWAP": "0.04165",
    "XAUT-USDT-SWAP": "4506.6",
    "LIGHT-USDT-SWAP": "0.629",
    "LAB-USDT-SWAP": "0.13512",
    "DOT-USD-SWAP": "2.09",
    "JTO-USDT-SWAP": "0.444",
    "FIL-USDT-SWAP": "1.486",
    "TIA-USDT-SWAP": "0.5502",
    "SKY-USDT-SWAP": "0.05916",
    "ENS-USDT-SWAP": "10.425",
    "BOME-USDT-SWAP": "0.0006972",
    "SOL-USD_UM-SWAP": "136.18",
    "PIEVERSE-USDT-SWAP": "0.4921",
    "0G-USDT-SWAP": "0.8649",
    "GAS-USDT-SWAP": "2.15",
    "SEI-USDT-SWAP": "0.1201",
    "OP-USDT-SWAP": "0.3176",
    "BIO-USDT-SWAP": "0.04398",
    "CORE-USDT-SWAP": "0.1234",
    "MOVE-USDT-SWAP": "0.03511",
    "GRASS-USDT-SWAP": "0.3632",
    "KMNO-USDT-SWAP": "0.05703",
    "SAPIEN-USDT-SWAP": "0.1424",
    "LTC-USD-SWAP": "81.35",
    "TON-USDT-SWAP": "1.738",
    "ATOM-USDT-SWAP": "2.6",
    "ETHW-USDT-SWAP": "0.5683",
    "ONE-USDT-SWAP": "0.004017",
    "SOLV-USDT-SWAP": "0.012852",
    "NIGHT-USDT-SWAP": "0.070728",
    "ETH-USD_UM-SWAP": "3086.69",
    "PENGU-USDT-SWAP": "0.011984",
    "ETHFI-USDT-SWAP": "0.7383",
    "SSV-USDT-SWAP": "3.983",
    "CVX-USDT-SWAP": "1.995",
    "ETC-USD-SWAP": "12.5",
    "RESOLV-USDT-SWAP": "0.07804",
    "MET-USDT-SWAP": "0.2522",
    "SAND-USDT-SWAP": "0.1198",
    "CELO-USDT-SWAP": "0.1266",
    "MANA-USDT-SWAP": "0.1452",
    "POPCAT-USDT-SWAP": "0.1002",
    "TAO-USDT-SWAP": "279.9",
    "AR-USDT-SWAP": "3.731",
    "FLOW-USDT-SWAP": "0.1013",
    "S-USDT-SWAP": "0.08478",
    "ARKM-USDT-SWAP": "0.2056",
    "WET-USDT-SWAP": "0.1475",
    "HUMA-USDT-SWAP": "0.02684",
    "APR-USDT-SWAP": "0.11942",
    "AEVO-USDT-SWAP": "0.04261",
    "BAT-USDT-SWAP": "0.204",
    "ZORA-USDT-SWAP": "0.03747",
    "BERA-USDT-SWAP": "0.5904",
    "HYPE-USDT-SWAP": "24.158",
    "WOO-USDT-SWAP": "0.02944",
    "PEOPLE-USDT-SWAP": "0.010306",
    "PENDLE-USDT-SWAP": "2.087",
    "SOON-USDT-SWAP": "0.377",
    "MMT-USDT-SWAP": "0.2553",
    "EIGEN-USDT-SWAP": "0.4057",
    "POL-USDT-SWAP": "0.1713",
    "PROVE-USDT-SWAP": "0.4639",
    "GMT-USDT-SWAP": "0.02045",
    "ZIL-USDT-SWAP": "0.005285",
    "TURTLE-USDT-SWAP": "0.06026",
    "PARTI-USDT-SWAP": "0.09045",
    "MASK-USDT-SWAP": "0.6637",
    "ENSO-USDT-SWAP": "0.6739",
    "BCH-USD-SWAP": "645.6",
    "NEAR-USDT-SWAP": "1.692",
    "COOKIE-USDT-SWAP": "0.04367",
    "SHELL-USDT-SWAP": "0.04699",
    "ZETA-USDT-SWAP": "0.0813",
    "XRP-USDT-SWAP": "2.0918",
    "HBAR-USDT-SWAP": "0.11706",
    "ICX-USDT-SWAP": "0.05865",
    "SPX-USDT-SWAP": "0.5842",
    "AXS-USDT-SWAP": "0.9532"
  }
}