{
  "updated_at": "2026-04-22 20:00:12 UTC",
  "count": 311,
  "source": "OKX SWAP",
  "prices": {
    "XPD-USDT-SWAP": "1554.53",
    "WIF-USDT-SWAP": "0.1966",
    "PI-USDT-SWAP": "0.1686",
    "EDGE-USDT-SWAP": "1.4555",
    "RECALL-USDT-SWAP": "0.04844",
    "SUSHI-USDT-SWAP": "0.2307",
    "RAVE-USDT-SWAP": "1.1343",
    "XLM-USDT-SWAP": "0.1786",
    "DASH-USDT-SWAP": "35.81",
    "TRUST-USDT-SWAP": "0.06736",
    "GPS-USDT-SWAP": "0.009268",
    "CRO-USDT-SWAP": "0.07032",
    "ACU-USDT-SWAP": "0.09655",
    "UNI-USDT-SWAP": "3.379",
    "STRK-USDT-SWAP": "0.04243",
    "NEIRO-USDT-SWAP": "0.00010075",
    "ZKP-USDT-SWAP": "0.07088",
    "SUI-USD-SWAP": "0.9573",
    "APE-USDT-SWAP": "0.10281",
    "MSTR-USDT-SWAP": "179.02",
    "ENJ-USDT-SWAP": "0.05777",
    "INJ-USDT-SWAP": "3.338",
    "RAY-USDT-SWAP": "0.6714",
    "OL-USDT-SWAP": "0.007436",
    "H-USDT-SWAP": "0.13325",
    "OKB-USDT-SWAP": "84.77",
    "APT-USDT-SWAP": "0.9541",
    "WCT-USDT-SWAP": "0.06041",
    "NEO-USDT-SWAP": "2.895",
    "SNX-USDT-SWAP": "0.2994",
    "LIT-USDT-SWAP": "0.899",
    "W-USDT-SWAP": "0.01303",
    "SYRUP-USDT-SWAP": "0.2349",
    "AVAX-USDT-SWAP": "9.468",
    "LPT-USDT-SWAP": "2.14",
    "ACT-USDT-SWAP": "0.01447",
    "FLOKI-USDT-SWAP": "0.00003305",
    "MSFT-USDT-SWAP": "433.41",
    "MEME-USDT-SWAP": "0.0005804",
    "DOGE-USDT-SWAP": "0.09662",
    "KGEN-USDT-SWAP": "0.1524",
    "MOODENG-USDT-SWAP": "0.05977",
    "NOT-USDT-SWAP": "0.0004078",
    "XCU-USDT-SWAP": "6.2052",
    "AERO-USDT-SWAP": "0.4205",
    "STX-USDT-SWAP": "0.229",
    "UNI-USD-SWAP": "3.38",
    "GIGGLE-USDT-SWAP": "36.69",
    "AVAX-USD-SWAP": "9.466",
    "AUCTION-USDT-SWAP": "4.79",
    "WAL-USDT-SWAP": "0.07353",
    "FIL-USD-SWAP": "0.9439",
    "ETH-USDT-SWAP": "2397.36",
    "SHIB-USDT-SWAP": "0.000006202",
    "ZRO-USDT-SWAP": "1.592",
    "GMX-USDT-SWAP": "6.87",
    "LAYER-USDT-SWAP": "0.08721",
    "ARB-USDT-SWAP": "0.13085",
    "MINA-USDT-SWAP": "0.0604",
    "IMX-USDT-SWAP": "0.1798",
    "LINEA-USDT-SWAP": "0.0034",
    "PUMP-USDT-SWAP": "0.001869",
    "VANA-USDT-SWAP": "1.425",
    "FOGO-USDT-SWAP": "0.01919",
    "BASED-USDT-SWAP": "0.11844",
    "ZBT-USDT-SWAP": "0.09998",
    "KITE-USDT-SWAP": "0.1486",
    "XTZ-USDT-SWAP": "0.3769",
    "SUI-USDT-SWAP": "0.9577",
    "ATH-USDT-SWAP": "0.006056",
    "AIXBT-USDT-SWAP": "0.02783",
    "TRIA-USDT-SWAP": "0.03443",
    "PIPPIN-USDT-SWAP": "0.02418",
    "ANIME-USDT-SWAP": "0.004762",
    "PEPE-USDT-SWAP": "0.000003864",
    "LRC-USDT-SWAP": "0.01733",
    "DYDX-USDT-SWAP": "0.14118",
    "LA-USDT-SWAP": "0.163",
    "GLM-USDT-SWAP": "0.1334",
    "CHZ-USDT-SWAP": "0.04674",
    "ACH-USDT-SWAP": "0.006318",
    "INIT-USDT-SWAP": "0.09067",
    "PLUME-USDT-SWAP": "0.012934",
    "BCH-USDT-SWAP": "462.4",
    "BLUR-USDT-SWAP": "0.03568",
    "SENT-USDT-SWAP": "0.01759",
    "ALLO-USDT-SWAP": "0.12099",
    "XPT-USDT-SWAP": "2082",
    "QQQ-USDT-SWAP": "655.28",
    "YGG-USDT-SWAP": "0.04039",
    "AAVE-USDT-SWAP": "94.45",
    "METIS-USDT-SWAP": "3.593",
    "ZAMA-USDT-SWAP": "0.02892",
    "ZK-USDT-SWAP": "0.01685",
    "MERL-USDT-SWAP": "0.04008",
    "EGLD-USDT-SWAP": "4.257",
    "AVNT-USDT-SWAP": "0.1481",
    "HMSTR-USDT-SWAP": "0.0001575",
    "AGLD-USDT-SWAP": "0.2739",
    "ONT-USDT-SWAP": "0.07713",
    "ALGO-USDT-SWAP": "0.10386",
    "ADA-USDT-SWAP": "0.2522",
    "TRUMP-USDT-SWAP": "2.934",
    "ME-USDT-SWAP": "0.10881",
    "NFLX-USDT-SWAP": "93.37",
    "GALA-USDT-SWAP": "0.003271",
    "BONK-USDT-SWAP": "0.000006456",
    "LUNA-USDT-SWAP": "0.05869",
    "XRP-USD-SWAP": "1.4408",
    "ADA-USD-SWAP": "0.2523",
    "XAG-USDT-SWAP": "77.78",
    "TRX-USDT-SWAP": "0.3292",
    "BEAT-USDT-SWAP": "0.5725",
    "BTC-USD-SWAP": "78833.4",
    "BABY-USDT-SWAP": "0.01641",
    "EDEN-USDT-SWAP": "0.03596",
    "PNUT-USDT-SWAP": "0.05713",
    "TEST01-USDT-SWAP": "0.06466",
    "BICO-USDT-SWAP": "0.02522",
    "IWM-USDT-SWAP": "276.1",
    "ICP-USDT-SWAP": "2.521",
    "META-USDT-SWAP": "675.36",
    "BAND-USDT-SWAP": "0.2264",
    "LDO-USDT-SWAP": "0.3925",
    "OFC-USDT-SWAP": "0.06732",
    "SATS-USDT-SWAP": "0.00000001507",
    "ZRX-USDT-SWAP": "0.11198",
    "ZEC-USDT-SWAP": "319.96",
    "MORPHO-USDT-SWAP": "1.945",
    "QTUM-USDT-SWAP": "0.9157",
    "SPACE-USDT-SWAP": "0.006065",
    "SIGN-USDT-SWAP": "0.01807",
    "AMZN-USDT-SWAP": "255.53",
    "TRUTH-USDT-SWAP": "0.009786",
    "YFI-USDT-SWAP": "2846",
    "1INCH-USDT-SWAP": "0.09667",
    "BRETT-USDT-SWAP": "0.007197",
    "SOL-USDT-SWAP": "87.34",
    "RIVER-USDT-SWAP": "6.528",
    "ETH-USD-SWAP": "2397.3",
    "FARTCOIN-USDT-SWAP": "0.2067",
    "API3-USDT-SWAP": "0.3143",
    "DOT-USDT-SWAP": "1.276",
    "HOOD-USDT-SWAP": "88.47",
    "JELLYJELLY-USDT-SWAP": "0.04565",
    "STABLE-USDT-SWAP": "0.02664",
    "F-USDT-SWAP": "0.00562",
    "DOOD-USDT-SWAP": "0.003199",
    "COAI-USDT-SWAP": "0.3164",
    "DOGE-USD-SWAP": "0.09665",
    "WLFI-USDT-SWAP": "0.07889",
    "USDC-USDT-SWAP": "0.999967",
    "IP-USDT-SWAP": "0.5461",
    "AT-USDT-SWAP": "0.1665",
    "LINK-USD-SWAP": "9.413",
    "WLD-USDT-SWAP": "0.2703",
    "LQTY-USDT-SWAP": "0.3044",
    "IOTA-USDT-SWAP": "0.05849",
    "TRB-USDT-SWAP": "18.81",
    "RVN-USDT-SWAP": "0.006022",
    "ORCL-USDT-SWAP": "187.18",
    "KSM-USDT-SWAP": "4.847",
    "BTC-USD_UM-SWAP": "78853.4",
    "CFX-USDT-SWAP": "0.05996",
    "SOPH-USDT-SWAP": "0.008941",
    "BARD-USDT-SWAP": "0.3257",
    "UMA-USDT-SWAP": "0.4902",
    "ZEN-USDT-SWAP": "6.178",
    "2Z-USDT-SWAP": "0.08427",
    "YB-USDT-SWAP": "0.11941",
    "CRCL-USDT-SWAP": "104.22",
    "RENDER-USDT-SWAP": "1.822",
    "JUP-USDT-SWAP": "0.1751",
    "MAGIC-USDT-SWAP": "0.065",
    "TURBO-USDT-SWAP": "0.0011824",
    "ORDI-USDT-SWAP": "4.552",
    "PYTH-USDT-SWAP": "0.04772",
    "ETC-USDT-SWAP": "8.55",
    "MEW-USDT-SWAP": "0.0006229",
    "CRV-USDT-SWAP": "0.2323",
    "MUBARAK-USDT-SWAP": "0.01395",
    "BIGTIME-USDT-SWAP": "0.01345",
    "ORDER-USDT-SWAP": "0.05551",
    "VIRTUAL-USDT-SWAP": "0.7049",
    "INTC-USDT-SWAP": "65.24",
    "THETA-USDT-SWAP": "0.2182",
    "ONDO-USDT-SWAP": "0.2641",
    "LTC-USDT-SWAP": "55.92",
    "SPK-USDT-SWAP": "0.03705",
    "A-USDT-SWAP": "0.08898",
    "ROBO-USDT-SWAP": "0.02144",
    "EWJ-USDT-SWAP": "87.75",
    "ASTER-USDT-SWAP": "0.6813",
    "BREV-USDT-SWAP": "0.1252",
    "IOST-USDT-SWAP": "0.001102",
    "BTC-USDT-SWAP": "78827.7",
    "EWY-USDT-SWAP": "155.67",
    "BNB-USDT-SWAP": "641.3",
    "SAHARA-USDT-SWAP": "0.02193",
    "MON-USDT-SWAP": "0.03406",
    "AAPL-USDT-SWAP": "273.3",
    "RSR-USDT-SWAP": "0.001775",
    "SPY-USDT-SWAP": "710.08",
    "KAITO-USDT-SWAP": "0.4042",
    "LINK-USDT-SWAP": "9.409",
    "NMR-USDT-SWAP": "9.23",
    "CRWV-USDT-SWAP": "122.62",
    "TSLA-USDT-SWAP": "387.5",
    "XPL-USDT-SWAP": "0.1027",
    "COMP-USDT-SWAP": "23.05",
    "ENA-USDT-SWAP": "0.10922",
    "CC-USDT-SWAP": "0.1526",
    "USELESS-USDT-SWAP": "0.04268",
    "PLTR-USDT-SWAP": "152.61",
    "RLS-USDT-SWAP": "0.002694",
    "HOME-USDT-SWAP": "0.01699",
    "SOL-USD-SWAP": "87.4",
    "GRT-USDT-SWAP": "0.02504",
    "LIGHT-USDT-SWAP": "0.16",
    "KAT-USDT-SWAP": "0.009612",
    "LAB-USDT-SWAP": "0.5798",
    "DOT-USD-SWAP": "1.276",
    "JTO-USDT-SWAP": "0.3435",
    "FIL-USDT-SWAP": "0.9434",
    "TIA-USDT-SWAP": "0.3775",
    "MU-USDT-SWAP": "488.2",
    "SKY-USDT-SWAP": "0.08346",
    "ENS-USDT-SWAP": "6.205",
    "NVDA-USDT-SWAP": "202.51",
    "BOME-USDT-SWAP": "0.000563",
    "SOL-USD_UM-SWAP": "87.35",
    "PIEVERSE-USDT-SWAP": "1.027",
    "XAU-USD_UM-SWAP": "4714.8",
    "0G-USDT-SWAP": "0.5874",
    "GAS-USDT-SWAP": "1.697",
    "SEI-USDT-SWAP": "0.06199",
    "OP-USDT-SWAP": "0.1257",
    "AMD-USDT-SWAP": "303.54",
    "BIO-USDT-SWAP": "0.02884",
    "CORE-USDT-SWAP": "0.063",
    "MOVE-USDT-SWAP": "0.01865",
    "NG-USDT-SWAP": "2.858",
    "GRASS-USDT-SWAP": "0.3949",
    "KMNO-USDT-SWAP": "0.02028",
    "SAPIEN-USDT-SWAP": "0.089",
    "OPN-USDT-SWAP": "0.185",
    "LTC-USD-SWAP": "55.93",
    "TON-USDT-SWAP": "1.373",
    "ATOM-USDT-SWAP": "1.872",
    "ETHW-USDT-SWAP": "0.3034",
    "ONE-USDT-SWAP": "0.002274",
    "COIN-USDT-SWAP": "205.92",
    "ESP-USDT-SWAP": "0.06925",
    "XAU-USDT-SWAP": "4733.1",
    "NIGHT-USDT-SWAP": "0.03703",
    "ETH-USD_UM-SWAP": "2397.84",
    "BSB-USDT-SWAP": "0.3477",
    "PENGU-USDT-SWAP": "0.008374",
    "ETHFI-USDT-SWAP": "0.4648",
    "SSV-USDT-SWAP": "2.775",
    "CVX-USDT-SWAP": "1.847",
    "ETC-USD-SWAP": "8.548",
    "RESOLV-USDT-SWAP": "0.03183",
    "UP-USDT-SWAP": "0.1988",
    "MET-USDT-SWAP": "0.1915",
    "SAND-USDT-SWAP": "0.07802",
    "CELO-USDT-SWAP": "0.08588",
    "SNDK-USDT-SWAP": "978.33",
    "MANA-USDT-SWAP": "0.09231",
    "POPCAT-USDT-SWAP": "0.06138",
    "TAO-USDT-SWAP": "245.8",
    "AR-USDT-SWAP": "2.055",
    "FLOW-USDT-SWAP": "0.03911",
    "S-USDT-SWAP": "0.04402",
    "AZTEC-USDT-SWAP": "0.02264",
    "ARKM-USDT-SWAP": "0.12323",
    "WET-USDT-SWAP": "0.10139",
    "HUMA-USDT-SWAP": "0.0228",
    "APR-USDT-SWAP": "0.1742",
    "AEVO-USDT-SWAP": "0.02582",
    "CL-USDT-SWAP": "92.57",
    "BAT-USDT-SWAP": "0.10324",
    "ZORA-USDT-SWAP": "0.0145",
    "BERA-USDT-SWAP": "0.4131",
    "TSM-USDT-SWAP": "388.19",
    "HYPE-USDT-SWAP": "40.93",
    "WOO-USDT-SWAP": "0.01875",
    "PEOPLE-USDT-SWAP": "0.007786",
    "PENDLE-USDT-SWAP": "1.344",
    "CHIP-USDT-SWAP": "0.10313",
    "SOON-USDT-SWAP": "0.1753",
    "MMT-USDT-SWAP": "0.1335",
    "EIGEN-USDT-SWAP": "0.1872",
    "POL-USDT-SWAP": "0.09391",
    "PROVE-USDT-SWAP": "0.2517",
    "GMT-USDT-SWAP": "0.011675",
    "ZIL-USDT-SWAP": "0.004091",
    "PARTI-USDT-SWAP": "0.04145",
    "MASK-USDT-SWAP": "0.4839",
    "ENSO-USDT-SWAP": "0.8064",
    "BCH-USD-SWAP": "462.5",
    "BZ-USDT-SWAP": "95.85",
    "NEAR-USDT-SWAP": "1.416",
    "SHELL-USDT-SWAP": "0.03368",
    "ZETA-USDT-SWAP": "0.05444",
    "GOOGL-USDT-SWAP": "339.68",
    "XRP-USDT-SWAP": "1.44",
    "HBAR-USDT-SWAP": "0.09157",
    "ICX-USDT-SWAP": "0.03834",
    "SPX-USDT-SWAP": "0.3912",
    "AXS-USDT-SWAP": "1.1182"
  }
}