{
  "updated_at": "2026-04-02 23:17:00 UTC",
  "count": 304,
  "source": "OKX SWAP",
  "prices": {
    "XPD-USDT-SWAP": "1511.37",
    "WIF-USDT-SWAP": "0.1789",
    "PI-USDT-SWAP": "0.1694",
    "EDGE-USDT-SWAP": "0.7692",
    "RECALL-USDT-SWAP": "0.03967",
    "SUSHI-USDT-SWAP": "0.1871",
    "RAVE-USDT-SWAP": "0.25794",
    "XLM-USDT-SWAP": "0.16247",
    "DASH-USDT-SWAP": "30.08",
    "TRUST-USDT-SWAP": "0.0633",
    "GPS-USDT-SWAP": "0.007771",
    "CRO-USDT-SWAP": "0.07006",
    "ACU-USDT-SWAP": "0.08551",
    "UNI-USDT-SWAP": "3.17",
    "STRK-USDT-SWAP": "0.03365",
    "NEIRO-USDT-SWAP": "0.00005404",
    "ZKP-USDT-SWAP": "0.06769",
    "SUI-USD-SWAP": "0.86",
    "APE-USDT-SWAP": "0.08223",
    "MSTR-USDT-SWAP": "120.2",
    "ENJ-USDT-SWAP": "0.02001",
    "INJ-USDT-SWAP": "2.734",
    "RAY-USDT-SWAP": "0.6153",
    "OL-USDT-SWAP": "0.01064",
    "H-USDT-SWAP": "0.08428",
    "OKB-USDT-SWAP": "83.32",
    "APT-USDT-SWAP": "0.8564",
    "WCT-USDT-SWAP": "0.05364",
    "NEO-USDT-SWAP": "2.654",
    "SNX-USDT-SWAP": "0.2777",
    "LIT-USDT-SWAP": "0.9582",
    "W-USDT-SWAP": "0.01396",
    "SYRUP-USDT-SWAP": "0.2094",
    "AVAX-USDT-SWAP": "8.727",
    "LPT-USDT-SWAP": "2.013",
    "ACT-USDT-SWAP": "0.01174",
    "FLOKI-USDT-SWAP": "0.00002649",
    "MSFT-USDT-SWAP": "373.74",
    "MEME-USDT-SWAP": "0.000507",
    "DOGE-USDT-SWAP": "0.09026",
    "KGEN-USDT-SWAP": "0.14387",
    "MOODENG-USDT-SWAP": "0.04512",
    "NOT-USDT-SWAP": "0.0003449",
    "XCU-USDT-SWAP": "5.6965",
    "AERO-USDT-SWAP": "0.3124",
    "STX-USDT-SWAP": "0.2133",
    "UNI-USD-SWAP": "3.17",
    "GIGGLE-USDT-SWAP": "21.97",
    "AVAX-USD-SWAP": "8.72",
    "AUCTION-USDT-SWAP": "4.599",
    "WAL-USDT-SWAP": "0.0698",
    "FIL-USD-SWAP": "0.8137",
    "ETH-USDT-SWAP": "2056.94",
    "SHIB-USDT-SWAP": "0.000005862",
    "ZRO-USDT-SWAP": "1.859",
    "GMX-USDT-SWAP": "6.185",
    "LAYER-USDT-SWAP": "0.0762",
    "ARB-USDT-SWAP": "0.09085",
    "MINA-USDT-SWAP": "0.05579",
    "IMX-USDT-SWAP": "0.1332",
    "LINEA-USDT-SWAP": "0.002951",
    "PUMP-USDT-SWAP": "0.001629",
    "VANA-USDT-SWAP": "1.209",
    "FOGO-USDT-SWAP": "0.01674",
    "BASED-USDT-SWAP": "0.0886",
    "ZBT-USDT-SWAP": "0.10822",
    "XTZ-USDT-SWAP": "0.3418",
    "SUI-USDT-SWAP": "0.8603",
    "ATH-USDT-SWAP": "0.006444",
    "AIXBT-USDT-SWAP": "0.02144",
    "TRIA-USDT-SWAP": "0.02371",
    "PIPPIN-USDT-SWAP": "0.06108",
    "ANIME-USDT-SWAP": "0.004485",
    "PEPE-USDT-SWAP": "0.000003325",
    "LRC-USDT-SWAP": "0.01813",
    "DYDX-USDT-SWAP": "0.09579",
    "LA-USDT-SWAP": "0.1893",
    "GLM-USDT-SWAP": "0.125",
    "CHZ-USDT-SWAP": "0.03886",
    "ACH-USDT-SWAP": "0.005952",
    "INIT-USDT-SWAP": "0.08036",
    "PLUME-USDT-SWAP": "0.009621",
    "BCH-USDT-SWAP": "444.8",
    "BLUR-USDT-SWAP": "0.01968",
    "SENT-USDT-SWAP": "0.01788",
    "ALLO-USDT-SWAP": "0.10535",
    "XPT-USDT-SWAP": "1994.8",
    "QQQ-USDT-SWAP": "584.76",
    "YGG-USDT-SWAP": "0.03411",
    "AAVE-USDT-SWAP": "93.95",
    "METIS-USDT-SWAP": "2.78",
    "ZAMA-USDT-SWAP": "0.02306",
    "ZK-USDT-SWAP": "0.01683",
    "MERL-USDT-SWAP": "0.02219",
    "EGLD-USDT-SWAP": "3.678",
    "AVNT-USDT-SWAP": "0.1254",
    "HMSTR-USDT-SWAP": "0.0001373",
    "AGLD-USDT-SWAP": "0.2374",
    "ONT-USDT-SWAP": "0.10703",
    "ALGO-USDT-SWAP": "0.10752",
    "ADA-USDT-SWAP": "0.2387",
    "TRUMP-USDT-SWAP": "2.811",
    "ME-USDT-SWAP": "0.09795",
    "NFLX-USDT-SWAP": "98.14",
    "GALA-USDT-SWAP": "0.002853",
    "BONK-USDT-SWAP": "0.000005636",
    "LUNA-USDT-SWAP": "0.0535",
    "XRP-USD-SWAP": "1.3165",
    "ADA-USD-SWAP": "0.2388",
    "XAG-USDT-SWAP": "72.97",
    "TRX-USDT-SWAP": "0.31509",
    "BEAT-USDT-SWAP": "0.34805",
    "BTC-USD-SWAP": "66916.6",
    "BABY-USDT-SWAP": "0.01396",
    "EDEN-USDT-SWAP": "0.03595",
    "PNUT-USDT-SWAP": "0.03904",
    "BICO-USDT-SWAP": "0.02234",
    "ICP-USDT-SWAP": "2.238",
    "META-USDT-SWAP": "575.28",
    "BAND-USDT-SWAP": "0.2067",
    "LDO-USDT-SWAP": "0.3127",
    "SATS-USDT-SWAP": "0.00000001043",
    "ZRX-USDT-SWAP": "0.10177",
    "ZEC-USDT-SWAP": "240.89",
    "MORPHO-USDT-SWAP": "1.5022",
    "QTUM-USDT-SWAP": "0.887",
    "SPACE-USDT-SWAP": "0.005626",
    "SIGN-USDT-SWAP": "0.03428",
    "AMZN-USDT-SWAP": "209.66",
    "TRUTH-USDT-SWAP": "0.009386",
    "YFI-USDT-SWAP": "2414",
    "1INCH-USDT-SWAP": "0.08748",
    "BRETT-USDT-SWAP": "0.005876",
    "SOL-USDT-SWAP": "78.89",
    "RIVER-USDT-SWAP": "12.143",
    "ETH-USD-SWAP": "2056.5",
    "FARTCOIN-USDT-SWAP": "0.1597",
    "API3-USDT-SWAP": "0.2655",
    "DOT-USDT-SWAP": "1.231",
    "HOOD-USDT-SWAP": "68.85",
    "JELLYJELLY-USDT-SWAP": "0.04481",
    "STABLE-USDT-SWAP": "0.02879",
    "F-USDT-SWAP": "0.004985",
    "DOOD-USDT-SWAP": "0.002839",
    "COAI-USDT-SWAP": "0.2777",
    "DOGE-USD-SWAP": "0.09022",
    "WLFI-USDT-SWAP": "0.09991",
    "USDC-USDT-SWAP": "0.999898",
    "IP-USDT-SWAP": "0.4967",
    "AT-USDT-SWAP": "0.16192",
    "LINK-USD-SWAP": "8.618",
    "WLD-USDT-SWAP": "0.2674",
    "LQTY-USDT-SWAP": "0.2713",
    "IOTA-USDT-SWAP": "0.05881",
    "TRB-USDT-SWAP": "14.58",
    "RVN-USDT-SWAP": "0.005657",
    "ORCL-USDT-SWAP": "146.09",
    "KSM-USDT-SWAP": "4.255",
    "BTC-USD_UM-SWAP": "66903.1",
    "CFX-USDT-SWAP": "0.05134",
    "SOPH-USDT-SWAP": "0.008082",
    "BARD-USDT-SWAP": "0.3064",
    "UMA-USDT-SWAP": "0.3876",
    "ZEN-USDT-SWAP": "5.07",
    "2Z-USDT-SWAP": "0.07638",
    "YB-USDT-SWAP": "0.11641",
    "CRCL-USDT-SWAP": "90.67",
    "RENDER-USDT-SWAP": "1.85",
    "JUP-USDT-SWAP": "0.1548",
    "MAGIC-USDT-SWAP": "0.05594",
    "TURBO-USDT-SWAP": "0.000944",
    "ORDI-USDT-SWAP": "2.269",
    "PYTH-USDT-SWAP": "0.03999",
    "ETC-USDT-SWAP": "7.862",
    "MEW-USDT-SWAP": "0.0005486",
    "CRV-USDT-SWAP": "0.2076",
    "MUBARAK-USDT-SWAP": "0.0109",
    "BIGTIME-USDT-SWAP": "0.01189",
    "ORDER-USDT-SWAP": "0.04784",
    "VIRTUAL-USDT-SWAP": "0.6344",
    "INTC-USDT-SWAP": "50.2",
    "THETA-USDT-SWAP": "0.1428",
    "ONDO-USDT-SWAP": "0.2574",
    "LTC-USDT-SWAP": "52.12",
    "SPK-USDT-SWAP": "0.02024",
    "A-USDT-SWAP": "0.07657",
    "ROBO-USDT-SWAP": "0.01953",
    "EWJ-USDT-SWAP": "85.1",
    "ASTER-USDT-SWAP": "0.6607",
    "BREV-USDT-SWAP": "0.109",
    "IOST-USDT-SWAP": "0.001057",
    "BTC-USDT-SWAP": "66923.7",
    "EWY-USDT-SWAP": "122.71",
    "BNB-USDT-SWAP": "582.9",
    "SAHARA-USDT-SWAP": "0.02115",
    "MON-USDT-SWAP": "0.0252",
    "AAPL-USDT-SWAP": "255.33",
    "RSR-USDT-SWAP": "0.001454",
    "SPY-USDT-SWAP": "653.87",
    "KAITO-USDT-SWAP": "0.4351",
    "LINK-USDT-SWAP": "8.621",
    "NMR-USDT-SWAP": "7.431",
    "TSLA-USDT-SWAP": "361.89",
    "XPL-USDT-SWAP": "0.12038",
    "COMP-USDT-SWAP": "16.5",
    "ENA-USDT-SWAP": "0.08129",
    "CC-USDT-SWAP": "0.14365",
    "USELESS-USDT-SWAP": "0.03247",
    "PLTR-USDT-SWAP": "148.44",
    "RLS-USDT-SWAP": "0.003466",
    "HOME-USDT-SWAP": "0.0184",
    "SOL-USD-SWAP": "78.94",
    "GRT-USDT-SWAP": "0.02359",
    "LIGHT-USDT-SWAP": "0.1667",
    "KAT-USDT-SWAP": "0.00897",
    "LAB-USDT-SWAP": "0.19213",
    "DOT-USD-SWAP": "1.232",
    "JTO-USDT-SWAP": "0.2609",
    "FIL-USDT-SWAP": "0.8135",
    "TIA-USDT-SWAP": "0.2849",
    "MU-USDT-SWAP": "365.11",
    "SKY-USDT-SWAP": "0.07487",
    "ENS-USDT-SWAP": "5.498",
    "NVDA-USDT-SWAP": "176.79",
    "BOME-USDT-SWAP": "0.0003679",
    "SOL-USD_UM-SWAP": "78.81",
    "PIEVERSE-USDT-SWAP": "0.5314",
    "XAU-USD_UM-SWAP": "4657",
    "0G-USDT-SWAP": "0.5264",
    "GAS-USDT-SWAP": "1.575",
    "SEI-USDT-SWAP": "0.05111",
    "OP-USDT-SWAP": "0.1061",
    "AMD-USDT-SWAP": "217.28",
    "BIO-USDT-SWAP": "0.01626",
    "CORE-USDT-SWAP": "0.02415",
    "MOVE-USDT-SWAP": "0.01773",
    "NG-USDT-SWAP": "2.8157",
    "GRASS-USDT-SWAP": "0.2759",
    "KMNO-USDT-SWAP": "0.01767",
    "SAPIEN-USDT-SWAP": "0.07081",
    "OPN-USDT-SWAP": "0.1887",
    "LTC-USD-SWAP": "52.11",
    "TON-USDT-SWAP": "1.233",
    "ATOM-USDT-SWAP": "1.664",
    "ETHW-USDT-SWAP": "0.2472",
    "ONE-USDT-SWAP": "0.002246",
    "COIN-USDT-SWAP": "171.68",
    "ESP-USDT-SWAP": "0.07697",
    "XAU-USDT-SWAP": "4670.1",
    "NIGHT-USDT-SWAP": "0.0457",
    "ETH-USD_UM-SWAP": "2056.23",
    "BSB-USDT-SWAP": "0.227",
    "PENGU-USDT-SWAP": "0.006208",
    "ETHFI-USDT-SWAP": "0.4411",
    "SSV-USDT-SWAP": "2.248",
    "CVX-USDT-SWAP": "1.697",
    "ETC-USD-SWAP": "7.859",
    "RESOLV-USDT-SWAP": "0.0437",
    "MET-USDT-SWAP": "0.1284",
    "SAND-USDT-SWAP": "0.0734",
    "CELO-USDT-SWAP": "0.0797",
    "SNDK-USDT-SWAP": "696.24",
    "MANA-USDT-SWAP": "0.0849",
    "POPCAT-USDT-SWAP": "0.04666",
    "TAO-USDT-SWAP": "299.3",
    "AR-USDT-SWAP": "1.666",
    "FLOW-USDT-SWAP": "0.02948",
    "S-USDT-SWAP": "0.04167",
    "AZTEC-USDT-SWAP": "0.01847",
    "ARKM-USDT-SWAP": "0.0952",
    "WET-USDT-SWAP": "0.10269",
    "HUMA-USDT-SWAP": "0.01295",
    "APR-USDT-SWAP": "0.17849",
    "AEVO-USDT-SWAP": "0.02261",
    "CL-USDT-SWAP": "111.33",
    "BAT-USDT-SWAP": "0.09413",
    "ZORA-USDT-SWAP": "0.01403",
    "BERA-USDT-SWAP": "0.4078",
    "TSM-USDT-SWAP": "338.32",
    "HYPE-USDT-SWAP": "35.204",
    "WOO-USDT-SWAP": "0.01652",
    "PEOPLE-USDT-SWAP": "0.006121",
    "PENDLE-USDT-SWAP": "1.078",
    "SOON-USDT-SWAP": "0.1143",
    "MMT-USDT-SWAP": "0.1081",
    "EIGEN-USDT-SWAP": "0.1523",
    "POL-USDT-SWAP": "0.09111",
    "PROVE-USDT-SWAP": "0.2298",
    "GMT-USDT-SWAP": "0.00972",
    "ZIL-USDT-SWAP": "0.003801",
    "PARTI-USDT-SWAP": "0.08503",
    "MASK-USDT-SWAP": "0.4353",
    "ENSO-USDT-SWAP": "0.9431",
    "BCH-USD-SWAP": "444.5",
    "BZ-USDT-SWAP": "108.56",
    "NEAR-USDT-SWAP": "1.1603",
    "SHELL-USDT-SWAP": "0.031",
    "ZETA-USDT-SWAP": "0.04676",
    "GOOGL-USDT-SWAP": "296.05",
    "XRP-USDT-SWAP": "1.3168",
    "HBAR-USDT-SWAP": "0.08775",
    "ICX-USDT-SWAP": "0.03496",
    "SPX-USDT-SWAP": "0.2607",
    "AXS-USDT-SWAP": "1.1086"
  }
}