{
  "updated_at": "2025-12-16 23:26:25 UTC",
  "count": 277,
  "source": "OKX SWAP",
  "prices": {
    "MOG-USDT-SWAP": "0.0000002438",
    "CETUS-USDT-SWAP": "0.02532",
    "WIF-USDT-SWAP": "0.3787",
    "PI-USDT-SWAP": "0.2",
    "RECALL-USDT-SWAP": "0.0869",
    "SUSHI-USDT-SWAP": "0.3008",
    "RAVE-USDT-SWAP": "0.30894",
    "XLM-USDT-SWAP": "0.2188",
    "DASH-USDT-SWAP": "40.87",
    "TRUST-USDT-SWAP": "0.1125",
    "GPS-USDT-SWAP": "0.005118",
    "CRO-USDT-SWAP": "0.09535",
    "UNI-USDT-SWAP": "5.18",
    "STRK-USDT-SWAP": "0.0949",
    "NEIRO-USDT-SWAP": "0.0001186",
    "SUI-USD-SWAP": "1.5064",
    "APE-USDT-SWAP": "0.2119",
    "ENJ-USDT-SWAP": "0.02813",
    "INJ-USDT-SWAP": "4.911",
    "RAY-USDT-SWAP": "0.9868",
    "SONIC-USDT-SWAP": "0.07221",
    "OL-USDT-SWAP": "0.01643",
    "H-USDT-SWAP": "0.06858",
    "OKB-USDT-SWAP": "109.36",
    "APT-USDT-SWAP": "1.587",
    "WCT-USDT-SWAP": "0.0728",
    "NEO-USDT-SWAP": "3.751",
    "SNX-USDT-SWAP": "0.4323",
    "W-USDT-SWAP": "0.03632",
    "SYRUP-USDT-SWAP": "0.2671",
    "AVAX-USDT-SWAP": "12.321",
    "LPT-USDT-SWAP": "3.314",
    "ACT-USDT-SWAP": "0.0206",
    "FLOKI-USDT-SWAP": "0.00004262",
    "MEME-USDT-SWAP": "0.001003",
    "DOGE-USDT-SWAP": "0.1315",
    "KGEN-USDT-SWAP": "0.21345",
    "MOODENG-USDT-SWAP": "0.07442",
    "NOT-USDT-SWAP": "0.0005305",
    "AERO-USDT-SWAP": "0.5389",
    "STX-USDT-SWAP": "0.2627",
    "UNI-USD-SWAP": "5.182",
    "ACE-USDT-SWAP": "0.2462",
    "GIGGLE-USDT-SWAP": "68.3",
    "AVAX-USD-SWAP": "12.317",
    "BLUAI-USDT-SWAP": "0.004728",
    "AUCTION-USDT-SWAP": "5.066",
    "WAL-USDT-SWAP": "0.1411",
    "FIL-USD-SWAP": "1.281",
    "ETH-USDT-SWAP": "2951.49",
    "SHIB-USDT-SWAP": "0.000007856",
    "ZRO-USDT-SWAP": "1.406",
    "GMX-USDT-SWAP": "8.067",
    "LAYER-USDT-SWAP": "0.1816",
    "ARB-USDT-SWAP": "0.1996",
    "MINA-USDT-SWAP": "0.0846",
    "IMX-USDT-SWAP": "0.251",
    "LINEA-USDT-SWAP": "0.00699",
    "PUMP-USDT-SWAP": "0.002336",
    "VANA-USDT-SWAP": "2.725",
    "ZBT-USDT-SWAP": "0.0846",
    "XTZ-USDT-SWAP": "0.4599",
    "SUI-USDT-SWAP": "1.5077",
    "ATH-USDT-SWAP": "0.00982",
    "AIXBT-USDT-SWAP": "0.03015",
    "PIPPIN-USDT-SWAP": "0.3576",
    "ANIME-USDT-SWAP": "0.005841",
    "PEPE-USDT-SWAP": "0.000004087",
    "LRC-USDT-SWAP": "0.05669",
    "DYDX-USDT-SWAP": "0.1822",
    "LA-USDT-SWAP": "0.3073",
    "JCT-USDT-SWAP": "0.001988",
    "GLM-USDT-SWAP": "0.2102",
    "CHZ-USDT-SWAP": "0.03028",
    "ACH-USDT-SWAP": "0.00842",
    "INIT-USDT-SWAP": "0.0855",
    "PLUME-USDT-SWAP": "0.01625",
    "BCH-USDT-SWAP": "545.6",
    "BLUR-USDT-SWAP": "0.02975",
    "SENT-USDT-SWAP": "0.046",
    "ALLO-USDT-SWAP": "0.1117",
    "YGG-USDT-SWAP": "0.0656",
    "OM-USDT-SWAP": "0.0753",
    "AAVE-USDT-SWAP": "185.06",
    "METIS-USDT-SWAP": "5.805",
    "ZK-USDT-SWAP": "0.02903",
    "ZENT-USDT-SWAP": "0.004242",
    "MERL-USDT-SWAP": "0.40169",
    "EGLD-USDT-SWAP": "6.903",
    "AVNT-USDT-SWAP": "0.2582",
    "HMSTR-USDT-SWAP": "0.0002013",
    "AGLD-USDT-SWAP": "0.2593",
    "ONT-USDT-SWAP": "0.06058",
    "NEWT-USDT-SWAP": "0.0998",
    "ALGO-USDT-SWAP": "0.1166",
    "ADA-USDT-SWAP": "0.3848",
    "FXS-USDT-SWAP": "0.6766",
    "TRUMP-USDT-SWAP": "5.281",
    "ME-USDT-SWAP": "0.2319",
    "GALA-USDT-SWAP": "0.006592",
    "BONK-USDT-SWAP": "0.000008589",
    "LUNA-USDT-SWAP": "0.13127",
    "XRP-USD-SWAP": "1.9257",
    "ADA-USD-SWAP": "0.3846",
    "TRX-USDT-SWAP": "0.28051",
    "BEAT-USDT-SWAP": "1.86576",
    "XAN-USDT-SWAP": "0.01437",
    "BTC-USD-SWAP": "87600.7",
    "BABY-USDT-SWAP": "0.01722",
    "EDEN-USDT-SWAP": "0.07373",
    "PNUT-USDT-SWAP": "0.07604",
    "BICO-USDT-SWAP": "0.04364",
    "ICP-USDT-SWAP": "3.061",
    "BAND-USDT-SWAP": "0.3293",
    "LDO-USDT-SWAP": "0.5535",
    "SATS-USDT-SWAP": "0.00000001582",
    "ZRX-USDT-SWAP": "0.1295",
    "ZEC-USDT-SWAP": "402.47",
    "MORPHO-USDT-SWAP": "1.1686",
    "QTUM-USDT-SWAP": "1.36",
    "SIGN-USDT-SWAP": "0.031",
    "TRUTH-USDT-SWAP": "0.017715",
    "YFI-USDT-SWAP": "3325",
    "1INCH-USDT-SWAP": "0.1609",
    "BRETT-USDT-SWAP": "0.01517",
    "SOL-USDT-SWAP": "128.49",
    "ETH-USD-SWAP": "2951.07",
    "FARTCOIN-USDT-SWAP": "0.3508",
    "API3-USDT-SWAP": "0.4468",
    "DOT-USDT-SWAP": "1.892",
    "JELLYJELLY-USDT-SWAP": "0.09295",
    "STABLE-USDT-SWAP": "0.01423",
    "F-USDT-SWAP": "0.006319",
    "DOOD-USDT-SWAP": "0.005396",
    "CAT-USDT-SWAP": "0.000002931",
    "COAI-USDT-SWAP": "0.5653",
    "DOGE-USD-SWAP": "0.13149",
    "CATI-USDT-SWAP": "0.06035",
    "WLFI-USDT-SWAP": "0.1344",
    "USDC-USDT-SWAP": "0.999956",
    "IP-USDT-SWAP": "1.691",
    "AT-USDT-SWAP": "0.0844",
    "LINK-USD-SWAP": "12.891",
    "WLD-USDT-SWAP": "0.5268",
    "LQTY-USDT-SWAP": "0.4191",
    "IOTA-USDT-SWAP": "0.0926",
    "TRB-USDT-SWAP": "19.93",
    "RVN-USDT-SWAP": "0.007241",
    "KSM-USDT-SWAP": "7.313",
    "BTC-USD_UM-SWAP": "87683.7",
    "CFX-USDT-SWAP": "0.07166",
    "TREE-USDT-SWAP": "0.1106",
    "SOPH-USDT-SWAP": "0.01326",
    "BARD-USDT-SWAP": "0.7687",
    "UMA-USDT-SWAP": "0.7362",
    "ZEN-USDT-SWAP": "8",
    "2Z-USDT-SWAP": "0.1106",
    "YB-USDT-SWAP": "0.4167",
    "RENDER-USDT-SWAP": "1.399",
    "GOAT-USDT-SWAP": "0.03501",
    "JUP-USDT-SWAP": "0.1928",
    "MAGIC-USDT-SWAP": "0.10235",
    "TURBO-USDT-SWAP": "0.00187",
    "ORDI-USDT-SWAP": "4.544",
    "PYTH-USDT-SWAP": "0.05992",
    "ETC-USDT-SWAP": "12.63",
    "MEW-USDT-SWAP": "0.000902",
    "CRV-USDT-SWAP": "0.3653",
    "MUBARAK-USDT-SWAP": "0.01566",
    "BIGTIME-USDT-SWAP": "0.02007",
    "ORDER-USDT-SWAP": "0.0934",
    "VIRTUAL-USDT-SWAP": "0.7214",
    "THETA-USDT-SWAP": "0.3257",
    "ONDO-USDT-SWAP": "0.4138",
    "LTC-USDT-SWAP": "79.06",
    "SPK-USDT-SWAP": "0.0208",
    "A-USDT-SWAP": "0.1626",
    "ASTER-USDT-SWAP": "0.7968",
    "IOST-USDT-SWAP": "0.001545",
    "BTC-USDT-SWAP": "87616.4",
    "BNB-USDT-SWAP": "872.2",
    "SAHARA-USDT-SWAP": "0.02744",
    "MON-USDT-SWAP": "0.02154",
    "PROMPT-USDT-SWAP": "0.05171",
    "RSR-USDT-SWAP": "0.002687",
    "KAITO-USDT-SWAP": "0.5418",
    "LINK-USDT-SWAP": "12.887",
    "NMR-USDT-SWAP": "10.298",
    "XPL-USDT-SWAP": "0.1336",
    "COMP-USDT-SWAP": "27.02",
    "ENA-USDT-SWAP": "0.2177",
    "CC-USDT-SWAP": "0.07195",
    "USELESS-USDT-SWAP": "0.0768",
    "RLS-USDT-SWAP": "0.014235",
    "HOME-USDT-SWAP": "0.02156",
    "SOL-USD-SWAP": "128.5",
    "GRT-USDT-SWAP": "0.0387",
    "XAUT-USDT-SWAP": "4304.4",
    "LIGHT-USDT-SWAP": "1.5029",
    "LAB-USDT-SWAP": "0.10853",
    "DOT-USD-SWAP": "1.891",
    "JTO-USDT-SWAP": "0.3626",
    "FIL-USDT-SWAP": "1.281",
    "TIA-USDT-SWAP": "0.5117",
    "SKY-USDT-SWAP": "0.05967",
    "ENS-USDT-SWAP": "9.98",
    "BOME-USDT-SWAP": "0.0006098",
    "SOL-USD_UM-SWAP": "128.35",
    "PIEVERSE-USDT-SWAP": "0.361",
    "0G-USDT-SWAP": "0.8378",
    "GAS-USDT-SWAP": "1.876",
    "SEI-USDT-SWAP": "0.1183",
    "OP-USDT-SWAP": "0.2923",
    "BIO-USDT-SWAP": "0.04544",
    "CORE-USDT-SWAP": "0.1549",
    "MOVE-USDT-SWAP": "0.03767",
    "GRASS-USDT-SWAP": "0.3029",
    "KMNO-USDT-SWAP": "0.05861",
    "SAPIEN-USDT-SWAP": "0.1385",
    "LTC-USD-SWAP": "79.02",
    "TON-USDT-SWAP": "1.542",
    "ATOM-USDT-SWAP": "2",
    "ETHW-USDT-SWAP": "0.5244",
    "ONE-USDT-SWAP": "0.003603",
    "SOLV-USDT-SWAP": "0.014876",
    "NIGHT-USDT-SWAP": "0.060667",
    "ETH-USD_UM-SWAP": "2947.15",
    "PENGU-USDT-SWAP": "0.010077",
    "ETHFI-USDT-SWAP": "0.7752",
    "SSV-USDT-SWAP": "3.297",
    "CVX-USDT-SWAP": "1.74",
    "ETC-USD-SWAP": "12.66",
    "RESOLV-USDT-SWAP": "0.0685",
    "MET-USDT-SWAP": "0.2436",
    "SAND-USDT-SWAP": "0.1204",
    "CELO-USDT-SWAP": "0.138",
    "PRCL-USDT-SWAP": "0.02086",
    "MANA-USDT-SWAP": "0.1339",
    "POPCAT-USDT-SWAP": "0.0918",
    "TAO-USDT-SWAP": "260.6",
    "AR-USDT-SWAP": "3.609",
    "FLOW-USDT-SWAP": "0.1877",
    "DEGEN-USDT-SWAP": "0.001365",
    "S-USDT-SWAP": "0.084",
    "ARKM-USDT-SWAP": "0.1979",
    "WET-USDT-SWAP": "0.2064",
    "HUMA-USDT-SWAP": "0.03095",
    "APR-USDT-SWAP": "0.10284",
    "AEVO-USDT-SWAP": "0.03815",
    "BAT-USDT-SWAP": "0.2295",
    "ZORA-USDT-SWAP": "0.05019",
    "BERA-USDT-SWAP": "0.6474",
    "HYPE-USDT-SWAP": "26.605",
    "WOO-USDT-SWAP": "0.024",
    "PEOPLE-USDT-SWAP": "0.00896",
    "PENDLE-USDT-SWAP": "2.028",
    "SOON-USDT-SWAP": "0.3347",
    "MMT-USDT-SWAP": "0.1919",
    "EIGEN-USDT-SWAP": "0.4036",
    "POL-USDT-SWAP": "0.1138",
    "PROVE-USDT-SWAP": "0.3829",
    "GMT-USDT-SWAP": "0.01494",
    "ZIL-USDT-SWAP": "0.004916",
    "TURTLE-USDT-SWAP": "0.0584",
    "PARTI-USDT-SWAP": "0.10035",
    "MASK-USDT-SWAP": "0.5719",
    "ENSO-USDT-SWAP": "0.7137",
    "BCH-USD-SWAP": "545.9",
    "NEAR-USDT-SWAP": "1.567",
    "COOKIE-USDT-SWAP": "0.04624",
    "SHELL-USDT-SWAP": "0.04788",
    "ZETA-USDT-SWAP": "0.07497",
    "XRP-USDT-SWAP": "1.9254",
    "HBAR-USDT-SWAP": "0.11405",
    "ICX-USDT-SWAP": "0.05573",
    "SPX-USDT-SWAP": "0.5477",
    "AXS-USDT-SWAP": "0.918"
  }
}