{
  "updated_at": "2026-03-07 17:01:18 UTC",
  "count": 315,
  "source": "OKX SWAP",
  "prices": {
    "XPD-USDT-SWAP": "1630.44",
    "WIF-USDT-SWAP": "0.1784",
    "PI-USDT-SWAP": "0.2262",
    "RECALL-USDT-SWAP": "0.04627",
    "SUSHI-USDT-SWAP": "0.196",
    "RAVE-USDT-SWAP": "0.28635",
    "XLM-USDT-SWAP": "0.15056",
    "DASH-USDT-SWAP": "32.47",
    "TRUST-USDT-SWAP": "0.06863",
    "GPS-USDT-SWAP": "0.008773",
    "CRO-USDT-SWAP": "0.07477",
    "ACU-USDT-SWAP": "0.09692",
    "UNI-USDT-SWAP": "3.804",
    "STRK-USDT-SWAP": "0.03793",
    "NEIRO-USDT-SWAP": "0.00006421",
    "ZKP-USDT-SWAP": "0.08927",
    "SUI-USD-SWAP": "0.9024",
    "APE-USDT-SWAP": "0.0951",
    "MSTR-USDT-SWAP": "132.43",
    "ENJ-USDT-SWAP": "0.01777",
    "INJ-USDT-SWAP": "2.874",
    "RAY-USDT-SWAP": "0.5768",
    "OL-USDT-SWAP": "0.01298",
    "H-USDT-SWAP": "0.15841",
    "OKB-USDT-SWAP": "100.06",
    "APT-USDT-SWAP": "0.9437",
    "WCT-USDT-SWAP": "0.05799",
    "NEO-USDT-SWAP": "2.495",
    "SNX-USDT-SWAP": "0.3127",
    "LIT-USDT-SWAP": "1.124",
    "W-USDT-SWAP": "0.01794",
    "SYRUP-USDT-SWAP": "0.2254",
    "AVAX-USDT-SWAP": "8.98",
    "LPT-USDT-SWAP": "2.22",
    "ACT-USDT-SWAP": "0.013",
    "FLOKI-USDT-SWAP": "0.00002766",
    "MSFT-USDT-SWAP": "407.43",
    "MEME-USDT-SWAP": "0.0005621",
    "DOGE-USDT-SWAP": "0.09021",
    "KGEN-USDT-SWAP": "0.19979",
    "MOODENG-USDT-SWAP": "0.04793",
    "NOT-USDT-SWAP": "0.0003623",
    "XCU-USDT-SWAP": "5.8668",
    "AERO-USDT-SWAP": "0.3301",
    "STX-USDT-SWAP": "0.2582",
    "UNI-USD-SWAP": "3.804",
    "GIGGLE-USDT-SWAP": "28.09",
    "AVAX-USD-SWAP": "8.978",
    "AUCTION-USDT-SWAP": "4.654",
    "WAL-USDT-SWAP": "0.07387",
    "FIL-USD-SWAP": "0.9644",
    "ETH-USDT-SWAP": "1977.4",
    "SHIB-USDT-SWAP": "0.000005358",
    "ZRO-USDT-SWAP": "1.92",
    "GMX-USDT-SWAP": "6.711",
    "LAYER-USDT-SWAP": "0.08162",
    "ARB-USDT-SWAP": "0.09729",
    "MINA-USDT-SWAP": "0.05453",
    "IMX-USDT-SWAP": "0.1543",
    "LINEA-USDT-SWAP": "0.003169",
    "PUMP-USDT-SWAP": "0.00191",
    "VANA-USDT-SWAP": "1.376",
    "FOGO-USDT-SWAP": "0.02393",
    "ZBT-USDT-SWAP": "0.07495",
    "XTZ-USDT-SWAP": "0.3645",
    "SUI-USDT-SWAP": "0.9025",
    "ATH-USDT-SWAP": "0.005894",
    "AIXBT-USDT-SWAP": "0.0248",
    "TRIA-USDT-SWAP": "0.02556",
    "PIPPIN-USDT-SWAP": "0.36662",
    "ANIME-USDT-SWAP": "0.004562",
    "PEPE-USDT-SWAP": "0.000003253",
    "LRC-USDT-SWAP": "0.03154",
    "DYDX-USDT-SWAP": "0.08229",
    "LA-USDT-SWAP": "0.2265",
    "GLM-USDT-SWAP": "0.1269",
    "CHZ-USDT-SWAP": "0.03406",
    "ACH-USDT-SWAP": "0.00689",
    "INIT-USDT-SWAP": "0.08775",
    "PLUME-USDT-SWAP": "0.011358",
    "BCH-USDT-SWAP": "451.1",
    "BLUR-USDT-SWAP": "0.01903",
    "SENT-USDT-SWAP": "0.0239",
    "ALLO-USDT-SWAP": "0.12414",
    "XPT-USDT-SWAP": "2150",
    "SUI-USD_UM-SWAP": "0.9024",
    "QQQ-USDT-SWAP": "595.88",
    "YGG-USDT-SWAP": "0.03783",
    "AAVE-USDT-SWAP": "109.62",
    "METIS-USDT-SWAP": "3.241",
    "LINK-USD_UM-SWAP": "",
    "ZAMA-USDT-SWAP": "0.01956",
    "ZK-USDT-SWAP": "0.01889",
    "MERL-USDT-SWAP": "0.03691",
    "EGLD-USDT-SWAP": "4.067",
    "AVNT-USDT-SWAP": "0.1556",
    "HMSTR-USDT-SWAP": "0.0001528",
    "AGLD-USDT-SWAP": "0.2658",
    "ONT-USDT-SWAP": "0.04079",
    "ALGO-USDT-SWAP": "0.08366",
    "ADA-USDT-SWAP": "0.2556",
    "TRUMP-USDT-SWAP": "3.035",
    "ME-USDT-SWAP": "0.1124",
    "BCH-USD_UM-SWAP": "",
    "GALA-USDT-SWAP": "0.00334",
    "BONK-USDT-SWAP": "0.000005734",
    "LUNA-USDT-SWAP": "0.06109",
    "XRP-USD-SWAP": "1.3602",
    "ADA-USD-SWAP": "0.2555",
    "XAG-USDT-SWAP": "84.58",
    "ZEC-USD_UM-SWAP": "",
    "TRX-USDT-SWAP": "0.28497",
    "BEAT-USDT-SWAP": "0.35385",
    "BTC-USD-SWAP": "67772.2",
    "BABY-USDT-SWAP": "0.01133",
    "EDEN-USDT-SWAP": "0.03611",
    "PNUT-USDT-SWAP": "0.0449",
    "PIPPIN-USD_UM-SWAP": "",
    "BICO-USDT-SWAP": "0.01912",
    "PEPE-USD_UM-SWAP": "0.000003524",
    "ICP-USDT-SWAP": "2.478",
    "PUMP-USD_UM-SWAP": "0.001906",
    "META-USDT-SWAP": "640.43",
    "BAND-USDT-SWAP": "0.2205",
    "LDO-USDT-SWAP": "0.288",
    "SATS-USDT-SWAP": "0.00000001078",
    "ZRX-USDT-SWAP": "0.102",
    "ZEC-USDT-SWAP": "206.71",
    "MORPHO-USDT-SWAP": "1.8373",
    "QTUM-USDT-SWAP": "0.8707",
    "SPACE-USDT-SWAP": "0.008161",
    "SIGN-USDT-SWAP": "0.04572",
    "AMZN-USDT-SWAP": "212.46",
    "TRUTH-USDT-SWAP": "0.009415",
    "YFI-USDT-SWAP": "2512",
    "1INCH-USDT-SWAP": "0.09221",
    "BRETT-USDT-SWAP": "0.007014",
    "SOL-USDT-SWAP": "83.58",
    "RIVER-USDT-SWAP": "17.177",
    "ETH-USD-SWAP": "1977.07",
    "FARTCOIN-USDT-SWAP": "0.152",
    "API3-USDT-SWAP": "0.2748",
    "DOT-USDT-SWAP": "1.473",
    "HOOD-USDT-SWAP": "76.51",
    "JELLYJELLY-USDT-SWAP": "0.0774",
    "STABLE-USDT-SWAP": "0.02886",
    "F-USDT-SWAP": "0.005334",
    "DOOD-USDT-SWAP": "0.002938",
    "COAI-USDT-SWAP": "0.306",
    "ASTER-USD_UM-SWAP": "0.7178",
    "DOGE-USD-SWAP": "0.0902",
    "WLFI-USDT-SWAP": "0.0975",
    "USDC-USDT-SWAP": "1.000062",
    "IP-USDT-SWAP": "0.8233",
    "AT-USDT-SWAP": "0.15124",
    "LINK-USD-SWAP": "8.761",
    "WLD-USDT-SWAP": "0.3821",
    "LQTY-USDT-SWAP": "0.2775",
    "IOTA-USDT-SWAP": "0.06389",
    "TRB-USDT-SWAP": "14.68",
    "RVN-USDT-SWAP": "0.005474",
    "DOGE-USD_UM-SWAP": "0.09137",
    "KSM-USDT-SWAP": "4.499",
    "AXS-USD_UM-SWAP": "1.1519",
    "BNB-USD_UM-SWAP": "",
    "BTC-USD_UM-SWAP": "67808.2",
    "CFX-USDT-SWAP": "0.04848",
    "SOPH-USDT-SWAP": "0.008452",
    "BARD-USDT-SWAP": "1.1584",
    "UMA-USDT-SWAP": "0.4131",
    "ZEN-USDT-SWAP": "5.406",
    "2Z-USDT-SWAP": "0.07366",
    "YB-USDT-SWAP": "0.1605",
    "CRCL-USDT-SWAP": "100.28",
    "RENDER-USDT-SWAP": "1.392",
    "JUP-USDT-SWAP": "0.1754",
    "MAGIC-USDT-SWAP": "0.06067",
    "TURBO-USDT-SWAP": "0.0009049",
    "ORDI-USDT-SWAP": "2.365",
    "PYTH-USDT-SWAP": "0.04679",
    "ETC-USDT-SWAP": "8.15",
    "MEW-USDT-SWAP": "0.0005794",
    "BEAT-USD_UM-SWAP": "",
    "CRV-USDT-SWAP": "0.235",
    "MUBARAK-USDT-SWAP": "0.0147",
    "BIGTIME-USDT-SWAP": "0.01308",
    "ORDER-USDT-SWAP": "0.05204",
    "VIRTUAL-USDT-SWAP": "0.6774",
    "INTC-USDT-SWAP": "43.31",
    "THETA-USDT-SWAP": "0.1796",
    "ONDO-USDT-SWAP": "0.2507",
    "LTC-USDT-SWAP": "53.82",
    "SPK-USDT-SWAP": "0.01976",
    "ADA-USD_UM-SWAP": "0.2748",
    "A-USDT-SWAP": "0.07666",
    "ROBO-USDT-SWAP": "0.0417",
    "RESOLV-USD_UM-SWAP": "",
    "ASTER-USDT-SWAP": "0.6936",
    "BREV-USDT-SWAP": "0.1518",
    "IOST-USDT-SWAP": "0.001105",
    "XPL-USD_UM-SWAP": "0.1158",
    "BTC-USDT-SWAP": "67792.5",
    "BNB-USDT-SWAP": "623.7",
    "SAHARA-USDT-SWAP": "0.02316",
    "MON-USDT-SWAP": "0.0219",
    "AAPL-USDT-SWAP": "255.71",
    "RSR-USDT-SWAP": "0.001649",
    "SPY-USDT-SWAP": "668.56",
    "KAITO-USDT-SWAP": "0.3558",
    "LINK-USDT-SWAP": "8.77",
    "NMR-USDT-SWAP": "7.764",
    "TSLA-USDT-SWAP": "394.42",
    "XPL-USDT-SWAP": "0.09608",
    "COMP-USDT-SWAP": "17.35",
    "ENA-USDT-SWAP": "0.10187",
    "CC-USDT-SWAP": "0.1525",
    "USELESS-USDT-SWAP": "0.0402",
    "PLTR-USDT-SWAP": "156.8",
    "RLS-USDT-SWAP": "0.003861",
    "HOME-USDT-SWAP": "0.02522",
    "SOL-USD-SWAP": "83.61",
    "GRT-USDT-SWAP": "0.02527",
    "LIGHT-USDT-SWAP": "0.1758",
    "KAT-USDT-SWAP": "0.01203",
    "LAB-USDT-SWAP": "0.15101",
    "DOT-USD-SWAP": "1.472",
    "JTO-USDT-SWAP": "0.2556",
    "FIL-USDT-SWAP": "0.9641",
    "TIA-USDT-SWAP": "0.3221",
    "MU-USDT-SWAP": "366.72",
    "SKY-USDT-SWAP": "0.0736",
    "HYPE-USD_UM-SWAP": "30.621",
    "ENS-USDT-SWAP": "5.823",
    "NVDA-USDT-SWAP": "176.62",
    "BOME-USDT-SWAP": "0.0003841",
    "SOL-USD_UM-SWAP": "83.39",
    "PIEVERSE-USDT-SWAP": "0.528",
    "XAU-USD_UM-SWAP": "5164.3",
    "0G-USDT-SWAP": "0.5972",
    "GAS-USDT-SWAP": "1.521",
    "SEI-USDT-SWAP": "0.06523",
    "OP-USDT-SWAP": "0.1175",
    "BIO-USDT-SWAP": "0.02088",
    "CORE-USDT-SWAP": "0.0802",
    "MOVE-USDT-SWAP": "0.02101",
    "GRASS-USDT-SWAP": "0.2784",
    "KMNO-USDT-SWAP": "0.02065",
    "SAPIEN-USDT-SWAP": "0.07353",
    "OPN-USDT-SWAP": "0.3061",
    "LTC-USD-SWAP": "53.8",
    "TON-USDT-SWAP": "1.312",
    "ATOM-USDT-SWAP": "1.796",
    "ETHW-USDT-SWAP": "0.301",
    "ONE-USDT-SWAP": "0.00237",
    "COIN-USDT-SWAP": "195.64",
    "ESP-USDT-SWAP": "0.11188",
    "XAU-USDT-SWAP": "5160.8",
    "NIGHT-USDT-SWAP": "0.057017",
    "ETH-USD_UM-SWAP": "1977.29",
    "XRP-USD_UM-SWAP": "1.406",
    "PENGU-USDT-SWAP": "0.006704",
    "ETHFI-USDT-SWAP": "0.5307",
    "SSV-USDT-SWAP": "2.661",
    "CVX-USDT-SWAP": "2.153",
    "ETC-USD-SWAP": "8.142",
    "RESOLV-USDT-SWAP": "0.0892",
    "MET-USDT-SWAP": "0.1623",
    "SAND-USDT-SWAP": "0.0795",
    "CELO-USDT-SWAP": "0.07414",
    "SNDK-USDT-SWAP": "515.41",
    "PIEVERSE-USD_UM-SWAP": "",
    "MANA-USDT-SWAP": "0.09175",
    "POPCAT-USDT-SWAP": "0.04974",
    "TAO-USDT-SWAP": "190.5",
    "AR-USDT-SWAP": "1.588",
    "FLOW-USDT-SWAP": "0.03999",
    "S-USDT-SWAP": "0.03892",
    "AZTEC-USDT-SWAP": "0.02183",
    "ARKM-USDT-SWAP": "0.1018",
    "FIL-USD_UM-SWAP": "0.9263",
    "NIGHT-USD_UM-SWAP": "",
    "WET-USDT-SWAP": "0.10737",
    "HUMA-USDT-SWAP": "0.01574",
    "APR-USDT-SWAP": "0.11408",
    "AEVO-USDT-SWAP": "0.02375",
    "CL-USDT-SWAP": "91.252",
    "BAT-USDT-SWAP": "0.0983",
    "ZORA-USDT-SWAP": "0.01874",
    "RIVER-USD_UM-SWAP": "16.007",
    "BERA-USDT-SWAP": "0.5374",
    "HYPE-USDT-SWAP": "30.75",
    "WOO-USDT-SWAP": "0.01709",
    "PEOPLE-USDT-SWAP": "0.006844",
    "PENDLE-USDT-SWAP": "1.219",
    "SOON-USDT-SWAP": "0.1596",
    "MMT-USDT-SWAP": "0.1174",
    "EIGEN-USDT-SWAP": "0.1793",
    "POL-USDT-SWAP": "0.09671",
    "PROVE-USDT-SWAP": "0.2656",
    "LTC-USD_UM-SWAP": "53.94",
    "GMT-USDT-SWAP": "0.01082",
    "ZIL-USDT-SWAP": "0.004075",
    "PARTI-USDT-SWAP": "0.08592",
    "MASK-USDT-SWAP": "0.4306",
    "ENSO-USDT-SWAP": "1.2222",
    "BCH-USD-SWAP": "451",
    "NEAR-USDT-SWAP": "1.2271",
    "SHELL-USDT-SWAP": "0.02732",
    "ZETA-USDT-SWAP": "0.05006",
    "GOOGL-USDT-SWAP": "297.43",
    "XRP-USDT-SWAP": "1.3603",
    "HBAR-USDT-SWAP": "0.09613",
    "ICX-USDT-SWAP": "0.03513",
    "SPX-USDT-SWAP": "0.3146",
    "AXS-USDT-SWAP": "1.1259"
  }
}